Workbook
Name Slicer_Category: #N/A
Name Slicer_Item_Name: #N/A
Name Slicer_Re_order_Level: #N/A
Name Slicer_Supplier: #N/A

Sheet Retail Dashboard
A6: Current Stock (Units) | D6: Inventory Value
A7: =SUM(Table5[Current stock]) -> 506999 | D7: =SUM(Table5[Inventory Value]) -> 4.8846161e+08
A8: Total Quantity Sold | D8: Stock Turnover
A9: =SUM(Table5[Total Qty Sold]) -> 5324 | D9: {=SUM(Table5[Total Revenue])/(SUM(Table5[Current stock]/600))} -> 10724.907

Sheet Inventory master
A1: Item ID | B1: Item Name | C1: Category | D1: Supplier | E1: Unit cost | F1: Unit Price | G1: Re order Level
A2: ITEM001-A | B2: 1x16 PLC Splitter | C2: Splitters | D2: Amphenol | E2: 1186.19 | F2: 1600.45 | G2: 36
A3: ITEM002-A | B3: Mechanical Splicer | C3: Splicers | D3: CommScope | E3: 808.73 | F3: 1190.93 | G3: 48
A4: ITEM003-A | B4: Single-Mode Fiber Cable 200m | C4: Fiber Optic Cables | D4: Belden | E4: 1199.96 | F4: 2088.64 | G4: 88
A5: ITEM004-A | B5: 1x8 PLC Splitter | C5: Splitters | D5: AFL | E5: 9.46 | F5: 17.25 | G5: 49
A6: ITEM005-A | B6: Fiber Adapter | C6: Accessories | D6: Corning Inc. | E6: 1844.49 | F6: 3404.2 | G6: 81
A7: ITEM006-A | B7: Fixed Attenuator 20dB | C7: Attenuators | D7: Corning Inc. | E7: 876.82 | F7: 1454.17 | G7: 93
A8: ITEM007-A | B8: Fusion Splicer | C8: Splicers | D8: Siemon | E8: 435.21 | F8: 846.51 | G8: 52
A9: ITEM008-A | B9: Mechanical Splicer | C9: Splicers | D9: CommScope | E9: 839.56 | F9: 1141.41 | G9: 54
A10: ITEM009-A | B10: 48-Port Fiber Patch Panel | C10: Patch Panels | D10: CommScope | E10: 494.2 | F10: 865.62 | G10: 43
A11: ITEM010-A | B11: 96-Port Fiber Patch Panel | C11: Patch Panels | D11: AFL | E11: 197.97 | F11: 277.51 | G11: 79
A12: ITEM011-A | B12: QSFP28 Transceiver | C12: Transceivers | D12: HellermannTyton | E12: 622.51 | F12: 852.41 | G12: 64
A13: ITEM012-A | B13: 12-Port Fiber Patch Panel | C13: Patch Panels | D13: Huber+Suhner | E13: 1245.47 | F13: 1515.52 | G13: 39
... A17: ITEM016-A | B17: 1x2 PLC Splitter | C17: Splitters | D17: Belden | E17: 205.86 | F17: 256.58 | G17: 55
A18: ITEM017-A | B18: Mechanical Splicer | C18: Splicers | D18: TE Connectivity | E18: 1484.52 | F18: 2666.95 | G18: 14
A19: ITEM018-A | B19: MTP UPC Connector | C19: Connectors | D19: AFL | E19: 1714.17 | F19: 2046.34 | G19: 45
A20: ITEM019-A | B20: 24-Port Fiber Patch Panel | C20: Patch Panels | D20: TE Connectivity | E20: 1773.05 | F20: 3098.97 | G20: 45
A21: ITEM020-A | B21: 96-Port Fiber Patch Panel | C21: Patch Panels | D21: Prysmian Group | E21: 577.51 | F21: 1028.16 | G21: 47
A22: ITEM021-A | B22: Fusion Splicer | C22: Splicers | D22: Corning Inc. | E22: 1448.33 | F22: 2578.14 | G22: 59
A23: ITEM022-A | B23: CFP Transceiver | C23: Transceivers | D23: Panduit | E23: 737.06 | F23: 844.2 | G23: 50
A24: ITEM023-A | B24: 1x2 PLC Splitter | C24: Splitters | D24: Siemon | E24: 839.54 | F24: 1239.65 | G24: 28
A25: ITEM024-A | B25: 1x32 PLC Splitter | C25: Splitters | D25: TE Connectivity | E25: 181.76 | F25: 301.07 | G25: 49
A26: ITEM025-A | B26: 48-Port Fiber Patch Panel | C26: Patch Panels | D26: Prysmian Group | E26: 996.3 | F26: 1436.94 | G26: 33
A27: ITEM026-A | B27: FC APC Connector | C27: Connectors | D27: AFL | E27: 630.68 | F27: 1168.53 | G27: 16
A28: ITEM027-A | B28: Armored Fiber Cable 200m | C28: Fiber Optic Cables | D28: Leviton | E28: 1075.74 | F28: 1742.62 | G28: 15
A29: ITEM028-A | B29: ST UPC Connector | C29: Connectors | D29: Prysmian Group | E29: 1249.66 | F29: 1832.34 | G29: 20
... A575: ITEM574-A | B575: ST APC Connector | C575: Connectors | D575: Leviton | E575: 394.32 | F575: 732.85 | G575: 58
A576: ITEM575-A | B576: Fusion Splicer | C576: Splicers | D576: Belden | E576: 1166.22 | F576: 2262.65 | G576: 17
A577: ITEM576-A | B577: Fusion Splicer | C577: Splicers | D577: Siemon | E577: 1075.34 | F577: 1659.57 | G577: 51
A578: ITEM577-A | B578: 48-Port Fiber Patch Panel | C578: Patch Panels | D578: Panduit | E578: 1178.28 | F578: 1470.76 | G578: 40
A579: ITEM578-A | B579: CFP Transceiver | C579: Transceivers | D579: TE Connectivity | E579: 258.25 | F579: 297.2 | G579: 47
A580: ITEM579-A | B580: Fiber Pigtail | C580: Accessories | D580: Belden | E580: 365.18 | F580: 560.56 | G580: 29
A581: ITEM580-A | B581: Mechanical Splicer | C581: Splicers | D581: TE Connectivity | E581: 1023.55 | F581: 1836.64 | G581: 93
A582: ITEM581-A | B582: Fixed Attenuator 5dB | C582: Attenuators | D582: CommScope | E582: 1307.17 | F582: 1515.58 | G582: 24
A583: ITEM582-A | B583: Fixed Attenuator 10dB | C583: Attenuators | D583: Amphenol | E583: 1965.61 | F583: 2418.8 | G583: 95
A584: ITEM583-A | B584: Fiber Pigtail | C584: Accessories | D584: Huber+Suhner | E584: 38.08 | F584: 58.81 | G584: 80
A585: ITEM584-A | B585: Fiber Optic Tester | C585: Tools | D585: Amphenol | E585: 886.72 | F585: 1222.36 | G585: 63
A586: ITEM585-A | B586: Fusion Splicer | C586: Splicers | D586: Prysmian Group | E586: 1869.43 | F586: 3035.66 | G586: 56
A587: ITEM586-A | B587: 48-Port Fiber Patch Panel | C587: Patch Panels | D587: CommScope | E587: 731.57 | F587: 1355.51 | G587: 60
A588: ITEM587-A | B588: 12-Port Fiber Patch Panel | C588: Patch Panels | D588: Belden | E588: 101.13 | F588: 157.76 | G588: 80
A589: ITEM588-A | B589: Fixed Attenuator 3dB | C589: Attenuators | D589: Prysmian Group | E589: 1488.15 | F589: 2339.59 | G589: 90
A590: ITEM589-A | B590: Mechanical Splicer | C590: Splicers | D590: Amphenol | E590: 1035.59 | F590: 1936.37 | G590: 100
A591: ITEM590-A | B591: Fiber Optic Stripper | C591: Tools | D591: HellermannTyton | E591: 175.51 | F591: 290.14 | G591: 90
A592: ITEM591-A | B592: Dome Enclosure | C592: Enclosures | D592: Siemon | E592: 363.59 | F592: 489.98 | G592: 66
A593: ITEM592-A | B593: 1x8 PLC Splitter | C593: Splitters | D593: Prysmian Group | E593: 1507.31 | F593: 2886.0 | G593: 79
A594: ITEM593-A | B594: Fixed Attenuator 1dB | C594: Attenuators | D594: Belden | E594: 88.33 | F594: 165.91 | G594: 92
... A601: ITEM600-A | B601: Fiber Jumper | C601: Accessories | D601: Belden | E601: 1680.72 | F601: 2126.26 | G601: 53

Sheet Opening stock
A1: Item ID | B1: ItemName | C1: Category | D1: Supplier | E1: Opening Qty
A2: ITEM001-A | B2: 1x16 PLC Splitter | C2: Splitters | D2: Amphenol | E2: ='Inventory master'!G2*2*7.5 -> 540
A3: ITEM002-A | B3: Mechanical Splicer | C3: Splicers | D3: CommScope | E3: ='Inventory master'!G3*2*7.5 -> 720
A4: ITEM003-A | B4: Single-Mode Fiber Cable 200m | C4: Fiber Optic Cables | D4: Belden | E4: ='Inventory master'!G4*2*7.5 -> 1320
A5: ITEM004-A | B5: 1x8 PLC Splitter | C5: Splitters | D5: AFL | E5: ='Inventory master'!G5*2*7.5 -> 735
A6: ITEM005-A | B6: Fiber Adapter | C6: Accessories | D6: Corning Inc. | E6: ='Inventory master'!G6*2*7.5 -> 1215
A7: ITEM006-A | B7: Fixed Attenuator 20dB | C7: Attenuators | D7: Corning Inc. | E7: ='Inventory master'!G7*2*7.5 -> 1395
A8: ITEM007-A | B8: Fusion Splicer | C8: Splicers | D8: Siemon | E8: ='Inventory master'!G8*2*7.5 -> 780
A9: ITEM008-A | B9: Mechanical Splicer | C9: Splicers | D9: CommScope | E9: ='Inventory master'!G9*2*7.5 -> 810
A10: ITEM009-A | B10: 48-Port Fiber Patch Panel | C10: Patch Panels | D10: CommScope | E10: ='Inventory master'!G10*2*7.5 -> 645
A11: ITEM010-A | B11: 96-Port Fiber Patch Panel | C11: Patch Panels | D11: AFL | E11: ='Inventory master'!G11*2*7.5 -> 1185
A12: ITEM011-A | B12: QSFP28 Transceiver | C12: Transceivers | D12: HellermannTyton | E12: ='Inventory master'!G12*2*7.5 -> 960
A13: ITEM012-A | B13: 12-Port Fiber Patch Panel | C13: Patch Panels | D13: Huber+Suhner | E13: ='Inventory master'!G13*2*7.5 -> 585
... A601: ITEM600-A | B601: Fiber Jumper | C601: Accessories | D601: Belden | E601: ='Inventory master'!G601*2*7.5 -> 795

Sheet Sales 
A1: Sales ID | B1: Date | C1: Item ID | D1: Quantity
A2: SALE001 | B2: 45946 | C2: ITEM115-A | D2: 100
A3: SALE002 | B3: 45542 | C3: ITEM229-A | D3: 4
A4: SALE003 | B4: 45984 | C4: ITEM559-A | D4: 14
A5: SALE004 | B5: 45324 | C5: ITEM031-A | D5: 8
A6: SALE005 | B6: 45809 | C6: ITEM028-A | D6: 18
A7: SALE006 | B7: 45721 | C7: ITEM226-A | D7: 9
A8: SALE007 | B8: 45298 | C8: ITEM164-A | D8: 11
A9: SALE008 | B9: 45576 | C9: ITEM160-A | D9: 50
A10: SALE009 | B10: 45396 | C10: ITEM095-A | D10: 12
A11: SALE010 | B11: 45644 | C11: ITEM271-A | D11: 38
A12: SALE011 | B12: 45891 | C12: ITEM342-A | D12: 7
A13: SALE012 | B13: 45891 | C13: ITEM001-A | D13: 100
... A605: SALE604 | B605: 45833 | C605: ITEM003-A | D605: 100

Sheet Purchases
A1: Purchase ID | B1: Date | C1: Item ID | D1: Quantity Purchased
A2: PUR001 | B2: 45946 | C2: ITEM115-A | D2: 400
A3: PUR002 | B3: 45573 | C3: ITEM251-A | D3: 2
A4: PUR003 | B4: 46046 | C4: ITEM105-A | D4: 8
A5: PUR004 | B5: 45850 | C5: ITEM090-A | D5: 7
A6: PUR005 | B6: 45324 | C6: ITEM031-A | D6: 1
A7: PUR006 | B7: 45530 | C7: ITEM518-A | D7: 7
A8: PUR007 | B8: 45866 | C8: ITEM204-A | D8: 9
A9: PUR008 | B9: 46010 | C9: ITEM559-A | D9: 4
A10: PUR009 | B10: 45751 | C10: ITEM285-A | D10: 11
A11: PUR010 | B11: 45298 | C11: ITEM164-A | D11: 9
A12: PUR011 | B12: 45640 | C12: ITEM285-A | D12: 2
A13: PUR012 | B13: 46073 | C13: ITEM345-A | D13: 1
... A601: PUR600 | B601: 45909 | C601: ITEM437-A | D601: 2

Sheet Inventory calculations
A1: Item ID | B1: Item Name | C1: Category | D1: Supplier | E1: Unit Cost | F1: Unit Price | G1: Re order Level | H1: Opening Stock | I1: Total Qty Sold | J1: Total qty Purchased | K1: Current stock | L1: Stock Validation | M1: Inventory Value | N1: Total Revenue | O1: Last sale Date | P1: Days Since Last Sale | Q1: Reorder Flag | R1: DEADSTOCK FLAG | S1: DEADSTOCK VALUE
A2: ='Inventory master'!A2 -> ITEM001-A | B2: ='Inventory master'!B2 -> 1x16 PLC Splitter | C2: ='Inventory master'!C2 -> Splitters | D2: ='Inventory master'!D2 -> Amphenol | E2: ='Inventory master'!E2 -> 1186.19 | F2: ='Inventory master'!F2 -> 1600.45 | G2: ='Inventory master'!G2 -> 36 | H2: =IFERROR(_xlfn.XLOOKUP(A2, 'Opening stock'!A2:A601, 'Opening stock'!E2:E601), "") -> 540 | I2: =IFERROR(SUMIF(Table3[Item ID],'Inventory calculations'!A2,Table3[Quantity]),0) -> 400 | J2: =IFERROR(SUMIF(Table4[Item ID],'Inventory calculations'!A2,Table4[Quantity Purchased]),0) -> 3 | K2: =H2+J2-I2 -> 143 | L2: =IF(K2<0,"STOCK ISSUE","OK") -> OK | M2: =K2*E2 -> 169625.17 | N2: =Table5[[#This Row],[Total Qty Sold]]*Table5[[#This Row],[Unit Price]] -> 640180 | O2: =IFERROR(_xlfn.MAXIFS(Table3[Date],Table3[Item ID],Table5[[#This Row],[Item ID]]),"") -> 45891 | P2: =IF(Table5[[#This Row],[Last sale Date]]="","Never Sold",TODAY()-Table5[[#This Row],[Last sale Date]]) -> 161 | Q2: =IF(Table5[[#This Row],[Re order Level]]<=Table5[[#This Row],[Current stock]],"ORDERASAP","OK BUT BE CHECKING") -> OK BUT BE CHECKING | R2: =IF(AND(ISNUMBER(B2), B2 > 60), "DEAD", "ACTIVE") -> ACTIVE | S2: =IF(Table5[[#This Row],[DEADSTOCK FLAG]]="DEAD",Table5[[#This Row],[Inventory Value]],0) -> 0
A3: ='Inventory master'!A3 -> ITEM002-A | B3: ='Inventory master'!B3 -> Mechanical Splicer | C3: ='Inventory master'!C3 -> Splicers | D3: ='Inventory master'!D3 -> CommScope | E3: ='Inventory master'!E3 -> 808.73 | F3: ='Inventory master'!F3 -> 1190.93 | G3: ='Inventory master'!G3 -> 48 | H3: =IFERROR(_xlfn.XLOOKUP(A3, 'Opening stock'!A3:A602, 'Opening stock'!E3:E602), "") -> 720 | I3: =IFERROR(SUMIF(Table3[Item ID],'Inventory calculations'!A3,Table3[Quantity]),0) -> 100 | J3: =IFERROR(SUMIF(Table4[Item ID],'Inventory calculations'!A3,Table4[Quantity Purchased]),0) -> 0 | K3: =H3+J3-I3 -> 620 | L3: =IF(K3<0,"STOCK ISSUE","OK") -> OK | M3: =K3*E3 -> 501412.6 | N3: =Table5[[#This Row],[Total Qty Sold]]*Table5[[#This Row],[Unit Price]] -> 119093 | O3: =IFERROR(_xlfn.MAXIFS(Table3[Date],Table3[Item ID],Table5[[#This Row],[Item ID]]),"") -> 45832 | P3: =IF(Table5[[#This Row],[Last sale Date]]="","Never Sold",TODAY()-Table5[[#This Row],[Last sale Date]]) -> 220 | Q3: =IF(Table5[[#This Row],[Re order Level]]<=Table5[[#This Row],[Current stock]],"ORDERASAP","OK BUT BE CHECKING") -> OK BUT BE CHECKING | R3: =IF(AND(ISNUMBER(B3), B3 > 60), "DEAD", "ACTIVE") -> ACTIVE | S3: =IF(Table5[[#This Row],[DEADSTOCK FLAG]]="DEAD",Table5[[#This Row],[Inventory Value]],0) -> 0
A4: ='Inventory master'!A4 -> ITEM003-A | B4: ='Inventory master'!B4 -> Single-Mode Fiber Cable 200m | C4: ='Inventory master'!C4 -> Fiber Optic Cables | D4: ='Inventory master'!D4 -> Belden | E4: ='Inventory master'!E4 -> 1199.96 | F4: ='Inventory master'!F4 -> 2088.64 | G4: ='Inventory master'!G4 -> 88 | H4: =IFERROR(_xlfn.XLOOKUP(A4, 'Opening stock'!A4:A603, 'Opening stock'!E4:E603), "") -> 1320 | I4: =IFERROR(SUMIF(Table3[Item ID],'Inventory calculations'!A4,Table3[Quantity]),0) -> 100 | J4: =IFERROR(SUMIF(Table4[Item ID],'Inventory calculations'!A4,Table4[Quantity Purchased]),0) -> 3 | K4: =H4+J4-I4 -> 1223 | L4: =IF(K4<0,"STOCK ISSUE","OK") -> OK | M4: =K4*E4 -> 1467551.1 | N4: =Table5[[#This Row],[Total Qty Sold]]*Table5[[#This Row],[Unit Price]] -> 208864 | O4: =IFERROR(_xlfn.MAXIFS(Table3[Date],Table3[Item ID],Table5[[#This Row],[Item ID]]),"") -> 45833 | P4: =IF(Table5[[#This Row],[Last sale Date]]="","Never Sold",TODAY()-Table5[[#This Row],[Last sale Date]]) -> 219 | Q4: =IF(Table5[[#This Row],[Re order Level]]<=Table5[[#This Row],[Current stock]],"ORDERASAP","OK BUT BE CHECKING") -> OK BUT BE CHECKING | R4: =IF(AND(ISNUMBER(B4), B4 > 60), "DEAD", "ACTIVE") -> ACTIVE | S4: =IF(Table5[[#This Row],[DEADSTOCK FLAG]]="DEAD",Table5[[#This Row],[Inventory Value]],0) -> 0
A5: ='Inventory master'!A5 -> ITEM004-A | B5: ='Inventory master'!B5 -> 1x8 PLC Splitter | C5: ='Inventory master'!C5 -> Splitters | D5: ='Inventory master'!D5 -> AFL | E5: ='Inventory master'!E5 -> 9.46 | F5: ='Inventory master'!F5 -> 17.25 | G5: ='Inventory master'!G5 -> 49 | H5: =IFERROR(_xlfn.XLOOKUP(A5, 'Opening stock'!A5:A604, 'Opening stock'!E5:E604), "") -> 735 | I5: =IFERROR(SUMIF(Table3[Item ID],'Inventory calculations'!A5,Table3[Quantity]),0) -> 0 | J5: =IFERROR(SUMIF(Table4[Item ID],'Inventory calculations'!A5,Table4[Quantity Purchased]),0) -> 0 | K5: =H5+J5-I5 -> 735 | L5: =IF(K5<0,"STOCK ISSUE","OK") -> OK | M5: =K5*E5 -> 6953.1 | N5: =Table5[[#This Row],[Total Qty Sold]]*Table5[[#This Row],[Unit Price]] -> 0 | P5: =IF(Table5[[#This Row],[Last sale Date]]="","Never Sold",TODAY()-Table5[[#This Row],[Last sale Date]]) -> Never Sold | Q5: =IF(Table5[[#This Row],[Re order Level]]<=Table5[[#This Row],[Current stock]],"ORDERASAP","OK BUT BE CHECKING") -> OK BUT BE CHECKING | R5: =IF(AND(ISNUMBER(B5), B5 > 60), "DEAD", "ACTIVE") -> ACTIVE | S5: =IF(Table5[[#This Row],[DEADSTOCK FLAG]]="DEAD",Table5[[#This Row],[Inventory Value]],0) -> 0
A6: ='Inventory master'!A6 -> ITEM005-A | B6: ='Inventory master'!B6 -> Fiber Adapter | C6: ='Inventory master'!C6 -> Accessories | D6: ='Inventory master'!D6 -> Corning Inc. | E6: ='Inventory master'!E6 -> 1844.49 | F6: ='Inventory master'!F6 -> 3404.2 | G6: ='Inventory master'!G6 -> 81 | H6: =IFERROR(_xlfn.XLOOKUP(A6, 'Opening stock'!A6:A605, 'Opening stock'!E6:E605), "") -> 1215 | I6: =IFERROR(SUMIF(Table3[Item ID],'Inventory calculations'!A6,Table3[Quantity]),0) -> 0 | J6: =IFERROR(SUMIF(Table4[Item ID],'Inventory calculations'!A6,Table4[Quantity Purchased]),0) -> 0 | K6: =H6+J6-I6 -> 1215 | L6: =IF(K6<0,"STOCK ISSUE","OK") -> OK | M6: =K6*E6 -> 2241055.4 | N6: =Table5[[#This Row],[Total Qty Sold]]*Table5[[#This Row],[Unit Price]] -> 0 | P6: =IF(Table5[[#This Row],[Last sale Date]]="","Never Sold",TODAY()-Table5[[#This Row],[Last sale Date]]) -> Never Sold | Q6: =IF(Table5[[#This Row],[Re order Level]]<=Table5[[#This Row],[Current stock]],"ORDERASAP","OK BUT BE CHECKING") -> OK BUT BE CHECKING | R6: =IF(AND(ISNUMBER(B6), B6 > 60), "DEAD", "ACTIVE") -> ACTIVE | S6: =IF(Table5[[#This Row],[DEADSTOCK FLAG]]="DEAD",Table5[[#This Row],[Inventory Value]],0) -> 0
A7: ='Inventory master'!A7 -> ITEM006-A | B7: ='Inventory master'!B7 -> Fixed Attenuator 20dB | C7: ='Inventory master'!C7 -> Attenuators | D7: ='Inventory master'!D7 -> Corning Inc. | E7: ='Inventory master'!E7 -> 876.82 | F7: ='Inventory master'!F7 -> 1454.17 | G7: ='Inventory master'!G7 -> 93 | H7: =IFERROR(_xlfn.XLOOKUP(A7, 'Opening stock'!A7:A606, 'Opening stock'!E7:E606), "") -> 1395 | I7: =IFERROR(SUMIF(Table3[Item ID],'Inventory calculations'!A7,Table3[Quantity]),0) -> 0 | J7: =IFERROR(SUMIF(Table4[Item ID],'Inventory calculations'!A7,Table4[Quantity Purchased]),0) -> 0 | K7: =H7+J7-I7 -> 1395 | L7: =IF(K7<0,"STOCK ISSUE","OK") -> OK | M7: =K7*E7 -> 1223163.9 | N7: =Table5[[#This Row],[Total Qty Sold]]*Table5[[#This Row],[Unit Price]] -> 0 | P7: =IF(Table5[[#This Row],[Last sale Date]]="","Never Sold",TODAY()-Table5[[#This Row],[Last sale Date]]) -> Never Sold | Q7: =IF(Table5[[#This Row],[Re order Level]]<=Table5[[#This Row],[Current stock]],"ORDERASAP","OK BUT BE CHECKING") -> OK BUT BE CHECKING | R7: =IF(AND(ISNUMBER(B7), B7 > 60), "DEAD", "ACTIVE") -> ACTIVE | S7: =IF(Table5[[#This Row],[DEADSTOCK FLAG]]="DEAD",Table5[[#This Row],[Inventory Value]],0) -> 0
A8: ='Inventory master'!A8 -> ITEM007-A | B8: ='Inventory master'!B8 -> Fusion Splicer | C8: ='Inventory master'!C8 -> Splicers | D8: ='Inventory master'!D8 -> Siemon | E8: ='Inventory master'!E8 -> 435.21 | F8: ='Inventory master'!F8 -> 846.51 | G8: ='Inventory master'!G8 -> 52 | H8: =IFERROR(_xlfn.XLOOKUP(A8, 'Opening stock'!A8:A607, 'Opening stock'!E8:E607), "") -> 780 | I8: =IFERROR(SUMIF(Table3[Item ID],'Inventory calculations'!A8,Table3[Quantity]),0) -> 0 | J8: =IFERROR(SUMIF(Table4[Item ID],'Inventory calculations'!A8,Table4[Quantity Purchased]),0) -> 2 | K8: =H8+J8-I8 -> 782 | L8: =IF(K8<0,"STOCK ISSUE","OK") -> OK | M8: =K8*E8 -> 340334.22 | N8: =Table5[[#This Row],[Total Qty Sold]]*Table5[[#This Row],[Unit Price]] -> 0 | P8: =IF(Table5[[#This Row],[Last sale Date]]="","Never Sold",TODAY()-Table5[[#This Row],[Last sale Date]]) -> Never Sold | Q8: =IF(Table5[[#This Row],[Re order Level]]<=Table5[[#This Row],[Current stock]],"ORDERASAP","OK BUT BE CHECKING") -> OK BUT BE CHECKING | R8: =IF(AND(ISNUMBER(B8), B8 > 60), "DEAD", "ACTIVE") -> ACTIVE | S8: =IF(Table5[[#This Row],[DEADSTOCK FLAG]]="DEAD",Table5[[#This Row],[Inventory Value]],0) -> 0
A9: ='Inventory master'!A9 -> ITEM008-A | B9: ='Inventory master'!B9 -> Mechanical Splicer | C9: ='Inventory master'!C9 -> Splicers | D9: ='Inventory master'!D9 -> CommScope | E9: ='Inventory master'!E9 -> 839.56 | F9: ='Inventory master'!F9 -> 1141.41 | G9: ='Inventory master'!G9 -> 54 | H9: =IFERROR(_xlfn.XLOOKUP(A9, 'Opening stock'!A9:A608, 'Opening stock'!E9:E608), "") -> 810 | I9: =IFERROR(SUMIF(Table3[Item ID],'Inventory calculations'!A9,Table3[Quantity]),0) -> 0 | J9: =IFERROR(SUMIF(Table4[Item ID],'Inventory calculations'!A9,Table4[Quantity Purchased]),0) -> 6 | K9: =H9+J9-I9 -> 816 | L9: =IF(K9<0,"STOCK ISSUE","OK") -> OK | M9: =K9*E9 -> 685080.96 | N9: =Table5[[#This Row],[Total Qty Sold]]*Table5[[#This Row],[Unit Price]] -> 0 | P9: =IF(Table5[[#This Row],[Last sale Date]]="","Never Sold",TODAY()-Table5[[#This Row],[Last sale Date]]) -> Never Sold | Q9: =IF(Table5[[#This Row],[Re order Level]]<=Table5[[#This Row],[Current stock]],"ORDERASAP","OK BUT BE CHECKING") -> OK BUT BE CHECKING | R9: =IF(AND(ISNUMBER(B9), B9 > 60), "DEAD", "ACTIVE") -> ACTIVE | S9: =IF(Table5[[#This Row],[DEADSTOCK FLAG]]="DEAD",Table5[[#This Row],[Inventory Value]],0) -> 0
A10: ='Inventory master'!A10 -> ITEM009-A | B10: ='Inventory master'!B10 -> 48-Port Fiber Patch Panel | C10: ='Inventory master'!C10 -> Patch Panels | D10: ='Inventory master'!D10 -> CommScope | E10: ='Inventory master'!E10 -> 494.2 | F10: ='Inventory master'!F10 -> 865.62 | G10: ='Inventory master'!G10 -> 43 | H10: =IFERROR(_xlfn.XLOOKUP(A10, 'Opening stock'!A10:A609, 'Opening stock'!E10:E609), "") -> 645 | I10: =IFERROR(SUMIF(Table3[Item ID],'Inventory calculations'!A10,Table3[Quantity]),0) -> 0 | J10: =IFERROR(SUMIF(Table4[Item ID],'Inventory calculations'!A10,Table4[Quantity Purchased]),0) -> 0 | K10: =H10+J10-I10 -> 645 | L10: =IF(K10<0,"STOCK ISSUE","OK") -> OK | M10: =K10*E10 -> 318759 | N10: =Table5[[#This Row],[Total Qty Sold]]*Table5[[#This Row],[Unit Price]] -> 0 | P10: =IF(Table5[[#This Row],[Last sale Date]]="","Never Sold",TODAY()-Table5[[#This Row],[Last sale Date]]) -> Never Sold | Q10: =IF(Table5[[#This Row],[Re order Level]]<=Table5[[#This Row],[Current stock]],"ORDERASAP","OK BUT BE CHECKING") -> OK BUT BE CHECKING | R10: =IF(AND(ISNUMBER(B10), B10 > 60), "DEAD", "ACTIVE") -> ACTIVE | S10: =IF(Table5[[#This Row],[DEADSTOCK FLAG]]="DEAD",Table5[[#This Row],[Inventory Value]],0) -> 0
A11: ='Inventory master'!A11 -> ITEM010-A | B11: ='Inventory master'!B11 -> 96-Port Fiber Patch Panel | C11: ='Inventory master'!C11 -> Patch Panels | D11: ='Inventory master'!D11 -> AFL | E11: ='Inventory master'!E11 -> 197.97 | F11: ='Inventory master'!F11 -> 277.51 | G11: ='Inventory master'!G11 -> 79 | H11: =IFERROR(_xlfn.XLOOKUP(A11, 'Opening stock'!A11:A610, 'Opening stock'!E11:E610), "") -> 1185 | I11: =IFERROR(SUMIF(Table3[Item ID],'Inventory calculations'!A11,Table3[Quantity]),0) -> 0 | J11: =IFERROR(SUMIF(Table4[Item ID],'Inventory calculations'!A11,Table4[Quantity Purchased]),0) -> 0 | K11: =H11+J11-I11 -> 1185 | L11: =IF(K11<0,"STOCK ISSUE","OK") -> OK | M11: =K11*E11 -> 234594.45 | N11: =Table5[[#This Row],[Total Qty Sold]]*Table5[[#This Row],[Unit Price]] -> 0 | P11: =IF(Table5[[#This Row],[Last sale Date]]="","Never Sold",TODAY()-Table5[[#This Row],[Last sale Date]]) -> Never Sold | Q11: =IF(Table5[[#This Row],[Re order Level]]<=Table5[[#This Row],[Current stock]],"ORDERASAP","OK BUT BE CHECKING") -> OK BUT BE CHECKING | R11: =IF(AND(ISNUMBER(B11), B11 > 60), "DEAD", "ACTIVE") -> ACTIVE | S11: =IF(Table5[[#This Row],[DEADSTOCK FLAG]]="DEAD",Table5[[#This Row],[Inventory Value]],0) -> 0
A12: ='Inventory master'!A12 -> ITEM011-A | B12: ='Inventory master'!B12 -> QSFP28 Transceiver | C12: ='Inventory master'!C12 -> Transceivers | D12: ='Inventory master'!D12 -> HellermannTyton | E12: ='Inventory master'!E12 -> 622.51 | F12: ='Inventory master'!F12 -> 852.41 | G12: ='Inventory master'!G12 -> 64 | H12: =IFERROR(_xlfn.XLOOKUP(A12, 'Opening stock'!A12:A611, 'Opening stock'!E12:E611), "") -> 960 | I12: =IFERROR(SUMIF(Table3[Item ID],'Inventory calculations'!A12,Table3[Quantity]),0) -> 0 | J12: =IFERROR(SUMIF(Table4[Item ID],'Inventory calculations'!A12,Table4[Quantity Purchased]),0) -> 0 | K12: =H12+J12-I12 -> 960 | L12: =IF(K12<0,"STOCK ISSUE","OK") -> OK | M12: =K12*E12 -> 597609.6 | N12: =Table5[[#This Row],[Total Qty Sold]]*Table5[[#This Row],[Unit Price]] -> 0 | P12: =IF(Table5[[#This Row],[Last sale Date]]="","Never Sold",TODAY()-Table5[[#This Row],[Last sale Date]]) -> Never Sold | Q12: =IF(Table5[[#This Row],[Re order Level]]<=Table5[[#This Row],[Current stock]],"ORDERASAP","OK BUT BE CHECKING") -> OK BUT BE CHECKING | R12: =IF(AND(ISNUMBER(B12), B12 > 60), "DEAD", "ACTIVE") -> ACTIVE | S12: =IF(Table5[[#This Row],[DEADSTOCK FLAG]]="DEAD",Table5[[#This Row],[Inventory Value]],0) -> 0
A13: ='Inventory master'!A13 -> ITEM012-A | B13: ='Inventory master'!B13 -> 12-Port Fiber Patch Panel | C13: ='Inventory master'!C13 -> Patch Panels | D13: ='Inventory master'!D13 -> Huber+Suhner | E13: ='Inventory master'!E13 -> 1245.47 | F13: ='Inventory master'!F13 -> 1515.52 | G13: ='Inventory master'!G13 -> 39 | H13: =IFERROR(_xlfn.XLOOKUP(A13, 'Opening stock'!A13:A612, 'Opening stock'!E13:E612), "") -> 585 | I13: =IFERROR(SUMIF(Table3[Item ID],'Inventory calculations'!A13,Table3[Quantity]),0) -> 0 | J13: =IFERROR(SUMIF(Table4[Item ID],'Inventory calculations'!A13,Table4[Quantity Purchased]),0) -> 8 | K13: =H13+J13-I13 -> 593 | L13: =IF(K13<0,"STOCK ISSUE","OK") -> OK | M13: =K13*E13 -> 738563.71 | N13: =Table5[[#This Row],[Total Qty Sold]]*Table5[[#This Row],[Unit Price]] -> 0 | P13: =IF(Table5[[#This Row],[Last sale Date]]="","Never Sold",TODAY()-Table5[[#This Row],[Last sale Date]]) -> Never Sold | Q13: =IF(Table5[[#This Row],[Re order Level]]<=Table5[[#This Row],[Current stock]],"ORDERASAP","OK BUT BE CHECKING") -> OK BUT BE CHECKING | R13: =IF(AND(ISNUMBER(B13), B13 > 60), "DEAD", "ACTIVE") -> ACTIVE | S13: =IF(Table5[[#This Row],[DEADSTOCK FLAG]]="DEAD",Table5[[#This Row],[Inventory Value]],0) -> 0
A14: ='Inventory master'!A14 -> ITEM013-A | B14: ='Inventory master'!B14 -> LC APC Connector | C14: ='Inventory master'!C14 -> Connectors | D14: ='Inventory master'!D14 -> Siemon | E14: ='Inventory master'!E14 -> 332.17 | F14: ='Inventory master'!F14 -> 567.28 | G14: ='Inventory master'!G14 -> 84 | H14: =IFERROR(_xlfn.XLOOKUP(A14, 'Opening stock'!A14:A613, 'Opening stock'!E14:E613), "") -> 1260 | I14: =IFERROR(SUMIF(Table3[Item ID],'Inventory calculations'!A14,Table3[Quantity]),0) -> 0 | J14: =IFERROR(SUMIF(Table4[Item ID],'Inventory calculations'!A14,Table4[Quantity Purchased]),0) -> 0 | K14: =H14+J14-I14 -> 1260 | L14: =IF(K14<0,"STOCK ISSUE","OK") -> OK | M14: =K14*E14 -> 418534.2 | N14: =Table5[[#This Row],[Total Qty Sold]]*Table5[[#This Row],[Unit Price]] -> 0 | P14: =IF(Table5[[#This Row],[Last sale Date]]="","Never Sold",TODAY()-Table5[[#This Row],[Last sale Date]]) -> Never Sold | Q14: =IF(Table5[[#This Row],[Re order Level]]<=Table5[[#This Row],[Current stock]],"ORDERASAP","OK BUT BE CHECKING") -> OK BUT BE CHECKING | R14: =IF(AND(ISNUMBER(B14), B14 > 60), "DEAD", "ACTIVE") -> ACTIVE | S14: =IF(Table5[[#This Row],[DEADSTOCK FLAG]]="DEAD",Table5[[#This Row],[Inventory Value]],0) -> 0
A15: ='Inventory master'!A15 -> ITEM014-A | B15: ='Inventory master'!B15 -> 1x16 PLC Splitter | C15: ='Inventory master'!C15 -> Splitters | D15: ='Inventory master'!D15 -> HellermannTyton | E15: ='Inventory master'!E15 -> 1172.09 | F15: ='Inventory master'!F15 -> 1796.09 | G15: ='Inventory master'!G15 -> 30 | H15: =IFERROR(_xlfn.XLOOKUP(A15, 'Opening stock'!A15:A614, 'Opening stock'!E15:E614), "") -> 450 | I15: =IFERROR(SUMIF(Table3[Item ID],'Inventory calculations'!A15,Table3[Quantity]),0) -> 0 | J15: =IFERROR(SUMIF(Table4[Item ID],'Inventory calculations'!A15,Table4[Quantity Purchased]),0) -> 0 | K15: =H15+J15-I15 -> 450 | L15: =IF(K15<0,"STOCK ISSUE","OK") -> OK | M15: =K15*E15 -> 527440.5 | N15: =Table5[[#This Row],[Total Qty Sold]]*Table5[[#This Row],[Unit Price]] -> 0 | P15: =IF(Table5[[#This Row],[Last sale Date]]="","Never Sold",TODAY()-Table5[[#This Row],[Last sale Date]]) -> Never Sold | Q15: =IF(Table5[[#This Row],[Re order Level]]<=Table5[[#This Row],[Current stock]],"ORDERASAP","OK BUT BE CHECKING") -> OK BUT BE CHECKING | R15: =IF(AND(ISNUMBER(B15), B15 > 60), "DEAD", "ACTIVE") -> ACTIVE | S15: =IF(Table5[[#This Row],[DEADSTOCK FLAG]]="DEAD",Table5[[#This Row],[Inventory Value]],0) -> 0
A16: ='Inventory master'!A16 -> ITEM015-A | B16: ='Inventory master'!B16 -> Fixed Attenuator 5dB | C16: ='Inventory master'!C16 -> Attenuators | D16: ='Inventory master'!D16 -> Belden | E16: ='Inventory master'!E16 -> 612.21 | F16: ='Inventory master'!F16 -> 798.2 | G16: ='Inventory master'!G16 -> 83 | H16: =IFERROR(_xlfn.XLOOKUP(A16, 'Opening stock'!A16:A615, 'Opening stock'!E16:E615), "") -> 1245 | I16: =IFERROR(SUMIF(Table3[Item ID],'Inventory calculations'!A16,Table3[Quantity]),0) -> 0 | J16: =IFERROR(SUMIF(Table4[Item ID],'Inventory calculations'!A16,Table4[Quantity Purchased]),0) -> 3 | K16: =H16+J16-I16 -> 1248 | L16: =IF(K16<0,"STOCK ISSUE","OK") -> OK | M16: =K16*E16 -> 764038.08 | N16: =Table5[[#This Row],[Total Qty Sold]]*Table5[[#This Row],[Unit Price]] -> 0 | P16: =IF(Table5[[#This Row],[Last sale Date]]="","Never Sold",TODAY()-Table5[[#This Row],[Last sale Date]]) -> Never Sold | Q16: =IF(Table5[[#This Row],[Re order Level]]<=Table5[[#This Row],[Current stock]],"ORDERASAP","OK BUT BE CHECKING") -> OK BUT BE CHECKING | R16: =IF(AND(ISNUMBER(B16), B16 > 60), "DEAD", "ACTIVE") -> ACTIVE | S16: =IF(Table5[[#This Row],[DEADSTOCK FLAG]]="DEAD",Table5[[#This Row],[Inventory Value]],0) -> 0
... A25: ='Inventory master'!A25 -> ITEM024-A | B25: ='Inventory master'!B25 -> 1x32 PLC Splitter | C25: ='Inventory master'!C25 -> Splitters | D25: ='Inventory master'!D25 -> TE Connectivity | E25: ='Inventory master'!E25 -> 181.76 | F25: ='Inventory master'!F25 -> 301.07 | G25: ='Inventory master'!G25 -> 49 | H25: =IFERROR(_xlfn.XLOOKUP(A25, 'Opening stock'!A25:A624, 'Opening stock'!E25:E624), "") -> 735 | I25: =IFERROR(SUMIF(Table3[Item ID],'Inventory calculations'!A25,Table3[Quantity]),0) -> 0 | J25: =IFERROR(SUMIF(Table4[Item ID],'Inventory calculations'!A25,Table4[Quantity Purchased]),0) -> 0 | K25: =H25+J25-I25 -> 735 | L25: =IF(K25<0,"STOCK ISSUE","OK") -> OK | M25: =K25*E25 -> 133593.6 | N25: =Table5[[#This Row],[Total Qty Sold]]*Table5[[#This Row],[Unit Price]] -> 0 | P25: =IF(Table5[[#This Row],[Last sale Date]]="","Never Sold",TODAY()-Table5[[#This Row],[Last sale Date]]) -> Never Sold | Q25: =IF(Table5[[#This Row],[Re order Level]]<=Table5[[#This Row],[Current stock]],"ORDERASAP","OK BUT BE CHECKING") -> OK BUT BE CHECKING | R25: =IF(AND(ISNUMBER(B25), B25 > 60), "DEAD", "ACTIVE") -> ACTIVE | S25: =IF(Table5[[#This Row],[DEADSTOCK FLAG]]="DEAD",Table5[[#This Row],[Inventory Value]],0) -> 0
A26: ='Inventory master'!A26 -> ITEM025-A | B26: ='Inventory master'!B26 -> 48-Port Fiber Patch Panel | C26: ='Inventory master'!C26 -> Patch Panels | D26: ='Inventory master'!D26 -> Prysmian Group | E26: ='Inventory master'!E26 -> 996.3 | F26: ='Inventory master'!F26 -> 1436.94 | G26: ='Inventory master'!G26 -> 33 | H26: =IFERROR(_xlfn.XLOOKUP(A26, 'Opening stock'!A26:A625, 'Opening stock'!E26:E625), "") -> 495 | I26: =IFERROR(SUMIF(Table3[Item ID],'Inventory calculations'!A26,Table3[Quantity]),0) -> 20 | J26: =IFERROR(SUMIF(Table4[Item ID],'Inventory calculations'!A26,Table4[Quantity Purchased]),0) -> 0 | K26: =H26+J26-I26 -> 475 | L26: =IF(K26<0,"STOCK ISSUE","OK") -> OK | M26: =K26*E26 -> 473242.5 | N26: =Table5[[#This Row],[Total Qty Sold]]*Table5[[#This Row],[Unit Price]] -> 28738.8 | O26: =IFERROR(_xlfn.MAXIFS(Table3[Date],Table3[Item ID],Table5[[#This Row],[Item ID]]),"") -> 45333 | P26: =IF(Table5[[#This Row],[Last sale Date]]="","Never Sold",TODAY()-Table5[[#This Row],[Last sale Date]]) -> 719 | Q26: =IF(Table5[[#This Row],[Re order Level]]<=Table5[[#This Row],[Current stock]],"ORDERASAP","OK BUT BE CHECKING") -> OK BUT BE CHECKING | R26: =IF(AND(ISNUMBER(B26), B26 > 60), "DEAD", "ACTIVE") -> ACTIVE | S26: =IF(Table5[[#This Row],[DEADSTOCK FLAG]]="DEAD",Table5[[#This Row],[Inventory Value]],0) -> 0
A27: ='Inventory master'!A27 -> ITEM026-A | B27: ='Inventory master'!B27 -> FC APC Connector | C27: ='Inventory master'!C27 -> Connectors | D27: ='Inventory master'!D27 -> AFL | E27: ='Inventory master'!E27 -> 630.68 | F27: ='Inventory master'!F27 -> 1168.53 | G27: ='Inventory master'!G27 -> 16 | H27: =IFERROR(_xlfn.XLOOKUP(A27, 'Opening stock'!A27:A626, 'Opening stock'!E27:E626), "") -> 240 | I27: =IFERROR(SUMIF(Table3[Item ID],'Inventory calculations'!A27,Table3[Quantity]),0) -> 0 | J27: =IFERROR(SUMIF(Table4[Item ID],'Inventory calculations'!A27,Table4[Quantity Purchased]),0) -> 0 | K27: =H27+J27-I27 -> 240 | L27: =IF(K27<0,"STOCK ISSUE","OK") -> OK | M27: =K27*E27 -> 151363.2 | N27: =Table5[[#This Row],[Total Qty Sold]]*Table5[[#This Row],[Unit Price]] -> 0 | P27: =IF(Table5[[#This Row],[Last sale Date]]="","Never Sold",TODAY()-Table5[[#This Row],[Last sale Date]]) -> Never Sold | Q27: =IF(Table5[[#This Row],[Re order Level]]<=Table5[[#This Row],[Current stock]],"ORDERASAP","OK BUT BE CHECKING") -> OK BUT BE CHECKING | R27: =IF(AND(ISNUMBER(B27), B27 > 60), "DEAD", "ACTIVE") -> ACTIVE | S27: =IF(Table5[[#This Row],[DEADSTOCK FLAG]]="DEAD",Table5[[#This Row],[Inventory Value]],0) -> 0
A28: ='Inventory master'!A28 -> ITEM027-A | B28: ='Inventory master'!B28 -> Armored Fiber Cable 200m | C28: ='Inventory master'!C28 -> Fiber Optic Cables | D28: ='Inventory master'!D28 -> Leviton | E28: ='Inventory master'!E28 -> 1075.74 | F28: ='Inventory master'!F28 -> 1742.62 | G28: ='Inventory master'!G28 -> 15 | H28: =IFERROR(_xlfn.XLOOKUP(A28, 'Opening stock'!A28:A627, 'Opening stock'!E28:E627), "") -> 225 | I28: =IFERROR(SUMIF(Table3[Item ID],'Inventory calculations'!A28,Table3[Quantity]),0) -> 0 | J28: =IFERROR(SUMIF(Table4[Item ID],'Inventory calculations'!A28,Table4[Quantity Purchased]),0) -> 0 | K28: =H28+J28-I28 -> 225 | L28: =IF(K28<0,"STOCK ISSUE","OK") -> OK | M28: =K28*E28 -> 242041.5 | N28: =Table5[[#This Row],[Total Qty Sold]]*Table5[[#This Row],[Unit Price]] -> 0 | P28: =IF(Table5[[#This Row],[Last sale Date]]="","Never Sold",TODAY()-Table5[[#This Row],[Last sale Date]]) -> Never Sold | Q28: =IF(Table5[[#This Row],[Re order Level]]<=Table5[[#This Row],[Current stock]],"ORDERASAP","OK BUT BE CHECKING") -> OK BUT BE CHECKING | R28: =IF(AND(ISNUMBER(B28), B28 > 60), "DEAD", "ACTIVE") -> ACTIVE | S28: =IF(Table5[[#This Row],[DEADSTOCK FLAG]]="DEAD",Table5[[#This Row],[Inventory Value]],0) -> 0
A29: ='Inventory master'!A29 -> ITEM028-A | B29: ='Inventory master'!B29 -> ST UPC Connector | C29: ='Inventory master'!C29 -> Connectors | D29: ='Inventory master'!D29 -> Prysmian Group | E29: ='Inventory master'!E29 -> 1249.66 | F29: ='Inventory master'!F29 -> 1832.34 | G29: ='Inventory master'!G29 -> 20 | H29: =IFERROR(_xlfn.XLOOKUP(A29, 'Opening stock'!A29:A628, 'Opening stock'!E29:E628), "") -> 300 | I29: =IFERROR(SUMIF(Table3[Item ID],'Inventory calculations'!A29,Table3[Quantity]),0) -> 18 | J29: =IFERROR(SUMIF(Table4[Item ID],'Inventory calculations'!A29,Table4[Quantity Purchased]),0) -> 20 | K29: =H29+J29-I29 -> 302 | L29: =IF(K29<0,"STOCK ISSUE","OK") -> OK | M29: =K29*E29 -> 377397.32 | N29: =Table5[[#This Row],[Total Qty Sold]]*Table5[[#This Row],[Unit Price]] -> 32982.12 | O29: =IFERROR(_xlfn.MAXIFS(Table3[Date],Table3[Item ID],Table5[[#This Row],[Item ID]]),"") -> 45809 | P29: =IF(Table5[[#This Row],[Last sale Date]]="","Never Sold",TODAY()-Table5[[#This Row],[Last sale Date]]) -> 243 | Q29: =IF(Table5[[#This Row],[Re order Level]]<=Table5[[#This Row],[Current stock]],"ORDERASAP","OK BUT BE CHECKING") -> OK BUT BE CHECKING | R29: =IF(AND(ISNUMBER(B29), B29 > 60), "DEAD", "ACTIVE") -> ACTIVE | S29: =IF(Table5[[#This Row],[DEADSTOCK FLAG]]="DEAD",Table5[[#This Row],[Inventory Value]],0) -> 0
A30: ='Inventory master'!A30 -> ITEM029-A | B30: ='Inventory master'!B30 -> 12-Port Fiber Patch Panel | C30: ='Inventory master'!C30 -> Patch Panels | D30: ='Inventory master'!D30 -> Corning Inc. | E30: ='Inventory master'!E30 -> 1997.37 | F30: ='Inventory master'!F30 -> 2857.07 | G30: ='Inventory master'!G30 -> 75 | H30: =IFERROR(_xlfn.XLOOKUP(A30, 'Opening stock'!A30:A629, 'Opening stock'!E30:E629), "") -> 1125 | I30: =IFERROR(SUMIF(Table3[Item ID],'Inventory calculations'!A30,Table3[Quantity]),0) -> 0 | J30: =IFERROR(SUMIF(Table4[Item ID],'Inventory calculations'!A30,Table4[Quantity Purchased]),0) -> 0 | K30: =H30+J30-I30 -> 1125 | L30: =IF(K30<0,"STOCK ISSUE","OK") -> OK | M30: =K30*E30 -> 2247041.2 | N30: =Table5[[#This Row],[Total Qty Sold]]*Table5[[#This Row],[Unit Price]] -> 0 | P30: =IF(Table5[[#This Row],[Last sale Date]]="","Never Sold",TODAY()-Table5[[#This Row],[Last sale Date]]) -> Never Sold | Q30: =IF(Table5[[#This Row],[Re order Level]]<=Table5[[#This Row],[Current stock]],"ORDERASAP","OK BUT BE CHECKING") -> OK BUT BE CHECKING | R30: =IF(AND(ISNUMBER(B30), B30 > 60), "DEAD", "ACTIVE") -> ACTIVE | S30: =IF(Table5[[#This Row],[DEADSTOCK FLAG]]="DEAD",Table5[[#This Row],[Inventory Value]],0) -> 0
A31: ='Inventory master'!A31 -> ITEM030-A | B31: ='Inventory master'!B31 -> QSFP Transceiver | C31: ='Inventory master'!C31 -> Transceivers | D31: ='Inventory master'!D31 -> AFL | E31: ='Inventory master'!E31 -> 1197.56 | F31: ='Inventory master'!F31 -> 2143.3 | G31: ='Inventory master'!G31 -> 88 | H31: =IFERROR(_xlfn.XLOOKUP(A31, 'Opening stock'!A31:A630, 'Opening stock'!E31:E630), "") -> 1320 | I31: =IFERROR(SUMIF(Table3[Item ID],'Inventory calculations'!A31,Table3[Quantity]),0) -> 0 | J31: =IFERROR(SUMIF(Table4[Item ID],'Inventory calculations'!A31,Table4[Quantity Purchased]),0) -> 0 | K31: =H31+J31-I31 -> 1320 | L31: =IF(K31<0,"STOCK ISSUE","OK") -> OK | M31: =K31*E31 -> 1580779.2 | N31: =Table5[[#This Row],[Total Qty Sold]]*Table5[[#This Row],[Unit Price]] -> 0 | P31: =IF(Table5[[#This Row],[Last sale Date]]="","Never Sold",TODAY()-Table5[[#This Row],[Last sale Date]]) -> Never Sold | Q31: =IF(Table5[[#This Row],[Re order Level]]<=Table5[[#This Row],[Current stock]],"ORDERASAP","OK BUT BE CHECKING") -> OK BUT BE CHECKING | R31: =IF(AND(ISNUMBER(B31), B31 > 60), "DEAD", "ACTIVE") -> ACTIVE | S31: =IF(Table5[[#This Row],[DEADSTOCK FLAG]]="DEAD",Table5[[#This Row],[Inventory Value]],0) -> 0
A32: ='Inventory master'!A32 -> ITEM031-A | B32: ='Inventory master'!B32 -> 1x8 PLC Splitter | C32: ='Inventory master'!C32 -> Splitters | D32: ='Inventory master'!D32 -> Belden | E32: ='Inventory master'!E32 -> 1807.04 | F32: ='Inventory master'!F32 -> 3164.85 | G32: ='Inventory master'!G32 -> 21 | H32: =IFERROR(_xlfn.XLOOKUP(A32, 'Opening stock'!A32:A631, 'Opening stock'!E32:E631), "") -> 315 | I32: =IFERROR(SUMIF(Table3[Item ID],'Inventory calculations'!A32,Table3[Quantity]),0) -> 8 | J32: =IFERROR(SUMIF(Table4[Item ID],'Inventory calculations'!A32,Table4[Quantity Purchased]),0) -> 1 | K32: =H32+J32-I32 -> 308 | L32: =IF(K32<0,"STOCK ISSUE","OK") -> OK | M32: =K32*E32 -> 556568.32 | N32: =Table5[[#This Row],[Total Qty Sold]]*Table5[[#This Row],[Unit Price]] -> 25318.8 | O32: =IFERROR(_xlfn.MAXIFS(Table3[Date],Table3[Item ID],Table5[[#This Row],[Item ID]]),"") -> 45324 | P32: =IF(Table5[[#This Row],[Last sale Date]]="","Never Sold",TODAY()-Table5[[#This Row],[Last sale Date]]) -> 728 | Q32: =IF(Table5[[#This Row],[Re order Level]]<=Table5[[#This Row],[Current stock]],"ORDERASAP","OK BUT BE CHECKING") -> OK BUT BE CHECKING | R32: =IF(AND(ISNUMBER(B32), B32 > 60), "DEAD", "ACTIVE") -> ACTIVE | S32: =IF(Table5[[#This Row],[DEADSTOCK FLAG]]="DEAD",Table5[[#This Row],[Inventory Value]],0) -> 0
A33: ='Inventory master'!A33 -> ITEM032-A | B33: ='Inventory master'!B33 -> MTP UPC Connector | C33: ='Inventory master'!C33 -> Connectors | D33: ='Inventory master'!D33 -> CommScope | E33: ='Inventory master'!E33 -> 1782.7 | F33: ='Inventory master'!F33 -> 2157.31 | G33: ='Inventory master'!G33 -> 13 | H33: =IFERROR(_xlfn.XLOOKUP(A33, 'Opening stock'!A33:A632, 'Opening stock'!E33:E632), "") -> 195 | I33: =IFERROR(SUMIF(Table3[Item ID],'Inventory calculations'!A33,Table3[Quantity]),0) -> 0 | J33: =IFERROR(SUMIF(Table4[Item ID],'Inventory calculations'!A33,Table4[Quantity Purchased]),0) -> 1 | K33: =H33+J33-I33 -> 196 | L33: =IF(K33<0,"STOCK ISSUE","OK") -> OK | M33: =K33*E33 -> 349409.2 | N33: =Table5[[#This Row],[Total Qty Sold]]*Table5[[#This Row],[Unit Price]] -> 0 | P33: =IF(Table5[[#This Row],[Last sale Date]]="","Never Sold",TODAY()-Table5[[#This Row],[Last sale Date]]) -> Never Sold | Q33: =IF(Table5[[#This Row],[Re order Level]]<=Table5[[#This Row],[Current stock]],"ORDERASAP","OK BUT BE CHECKING") -> OK BUT BE CHECKING | R33: =IF(AND(ISNUMBER(B33), B33 > 60), "DEAD", "ACTIVE") -> ACTIVE | S33: =IF(Table5[[#This Row],[DEADSTOCK FLAG]]="DEAD",Table5[[#This Row],[Inventory Value]],0) -> 0
A34: ='Inventory master'!A34 -> ITEM033-A | B34: ='Inventory master'!B34 -> Fiber Cleaner | C34: ='Inventory master'!C34 -> Accessories | D34: ='Inventory master'!D34 -> Corning Inc. | E34: ='Inventory master'!E34 -> 373.91 | F34: ='Inventory master'!F34 -> 532.56 | G34: ='Inventory master'!G34 -> 59 | H34: =IFERROR(_xlfn.XLOOKUP(A34, 'Opening stock'!A34:A633, 'Opening stock'!E34:E633), "") -> 885 | I34: =IFERROR(SUMIF(Table3[Item ID],'Inventory calculations'!A34,Table3[Quantity]),0) -> 0 | J34: =IFERROR(SUMIF(Table4[Item ID],'Inventory calculations'!A34,Table4[Quantity Purchased]),0) -> 0 | K34: =H34+J34-I34 -> 885 | L34: =IF(K34<0,"STOCK ISSUE","OK") -> OK | M34: =K34*E34 -> 330910.35 | N34: =Table5[[#This Row],[Total Qty Sold]]*Table5[[#This Row],[Unit Price]] -> 0 | P34: =IF(Table5[[#This Row],[Last sale Date]]="","Never Sold",TODAY()-Table5[[#This Row],[Last sale Date]]) -> Never Sold | Q34: =IF(Table5[[#This Row],[Re order Level]]<=Table5[[#This Row],[Current stock]],"ORDERASAP","OK BUT BE CHECKING") -> OK BUT BE CHECKING | R34: =IF(AND(ISNUMBER(B34), B34 > 60), "DEAD", "ACTIVE") -> ACTIVE | S34: =IF(Table5[[#This Row],[DEADSTOCK FLAG]]="DEAD",Table5[[#This Row],[Inventory Value]],0) -> 0
A35: ='Inventory master'!A35 -> ITEM034-A | B35: ='Inventory master'!B35 -> MTP UPC Connector | C35: ='Inventory master'!C35 -> Connectors | D35: ='Inventory master'!D35 -> TE Connectivity | E35: ='Inventory master'!E35 -> 553.01 | F35: ='Inventory master'!F35 -> 625.22 | G35: ='Inventory master'!G35 -> 77 | H35: =IFERROR(_xlfn.XLOOKUP(A35, 'Opening stock'!A35:A634, 'Opening stock'!E35:E634), "") -> 1155 | I35: =IFERROR(SUMIF(Table3[Item ID],'Inventory calculations'!A35,Table3[Quantity]),0) -> 0 | J35: =IFERROR(SUMIF(Table4[Item ID],'Inventory calculations'!A35,Table4[Quantity Purchased]),0) -> 8 | K35: =H35+J35-I35 -> 1163 | L35: =IF(K35<0,"STOCK ISSUE","OK") -> OK | M35: =K35*E35 -> 643150.63 | N35: =Table5[[#This Row],[Total Qty Sold]]*Table5[[#This Row],[Unit Price]] -> 0 | P35: =IF(Table5[[#This Row],[Last sale Date]]="","Never Sold",TODAY()-Table5[[#This Row],[Last sale Date]]) -> Never Sold | Q35: =IF(Table5[[#This Row],[Re order Level]]<=Table5[[#This Row],[Current stock]],"ORDERASAP","OK BUT BE CHECKING") -> OK BUT BE CHECKING | R35: =IF(AND(ISNUMBER(B35), B35 > 60), "DEAD", "ACTIVE") -> ACTIVE | S35: =IF(Table5[[#This Row],[DEADSTOCK FLAG]]="DEAD",Table5[[#This Row],[Inventory Value]],0) -> 0
A36: ='Inventory master'!A36 -> ITEM035-A | B36: ='Inventory master'!B36 -> Fixed Attenuator 15dB | C36: ='Inventory master'!C36 -> Attenuators | D36: ='Inventory master'!D36 -> Leviton | E36: ='Inventory master'!E36 -> 1841.77 | F36: ='Inventory master'!F36 -> 3528.41 | G36: ='Inventory master'!G36 -> 82 | H36: =IFERROR(_xlfn.XLOOKUP(A36, 'Opening stock'!A36:A635, 'Opening stock'!E36:E635), "") -> 1230 | I36: =IFERROR(SUMIF(Table3[Item ID],'Inventory calculations'!A36,Table3[Quantity]),0) -> 0 | J36: =IFERROR(SUMIF(Table4[Item ID],'Inventory calculations'!A36,Table4[Quantity Purchased]),0) -> 6 | K36: =H36+J36-I36 -> 1236 | L36: =IF(K36<0,"STOCK ISSUE","OK") -> OK | M36: =K36*E36 -> 2276427.7 | N36: =Table5[[#This Row],[Total Qty Sold]]*Table5[[#This Row],[Unit Price]] -> 0 | P36: =IF(Table5[[#This Row],[Last sale Date]]="","Never Sold",TODAY()-Table5[[#This Row],[Last sale Date]]) -> Never Sold | Q36: =IF(Table5[[#This Row],[Re order Level]]<=Table5[[#This Row],[Current stock]],"ORDERASAP","OK BUT BE CHECKING") -> OK BUT BE CHECKING | R36: =IF(AND(ISNUMBER(B36), B36 > 60), "DEAD", "ACTIVE") -> ACTIVE | S36: =IF(Table5[[#This Row],[DEADSTOCK FLAG]]="DEAD",Table5[[#This Row],[Inventory Value]],0) -> 0
A37: ='Inventory master'!A37 -> ITEM036-A | B37: ='Inventory master'!B37 -> Fiber Cleaner | C37: ='Inventory master'!C37 -> Accessories | D37: ='Inventory master'!D37 -> Amphenol | E37: ='Inventory master'!E37 -> 220.13 | F37: ='Inventory master'!F37 -> 267.32 | G37: ='Inventory master'!G37 -> 45 | H37: =IFERROR(_xlfn.XLOOKUP(A37, 'Opening stock'!A37:A636, 'Opening stock'!E37:E636), "") -> 675 | I37: =IFERROR(SUMIF(Table3[Item ID],'Inventory calculations'!A37,Table3[Quantity]),0) -> 0 | J37: =IFERROR(SUMIF(Table4[Item ID],'Inventory calculations'!A37,Table4[Quantity Purchased]),0) -> 0 | K37: =H37+J37-I37 -> 675 | L37: =IF(K37<0,"STOCK ISSUE","OK") -> OK | M37: =K37*E37 -> 148587.75 | N37: =Table5[[#This Row],[Total Qty Sold]]*Table5[[#This Row],[Unit Price]] -> 0 | P37: =IF(Table5[[#This Row],[Last sale Date]]="","Never Sold",TODAY()-Table5[[#This Row],[Last sale Date]]) -> Never Sold | Q37: =IF(Table5[[#This Row],[Re order Level]]<=Table5[[#This Row],[Current stock]],"ORDERASAP","OK BUT BE CHECKING") -> OK BUT BE CHECKING | R37: =IF(AND(ISNUMBER(B37), B37 > 60), "DEAD", "ACTIVE") -> ACTIVE | S37: =IF(Table5[[#This Row],[DEADSTOCK FLAG]]="DEAD",Table5[[#This Row],[Inventory Value]],0) -> 0
A38: ='Inventory master'!A38 -> ITEM037-A | B38: ='Inventory master'!B38 -> Fiber Jumper | C38: ='Inventory master'!C38 -> Accessories | D38: ='Inventory master'!D38 -> Corning Inc. | E38: ='Inventory master'!E38 -> 1663.18 | F38: ='Inventory master'!F38 -> 2231.44 | G38: ='Inventory master'!G38 -> 77 | H38: =IFERROR(_xlfn.XLOOKUP(A38, 'Opening stock'!A38:A637, 'Opening stock'!E38:E637), "") -> 1155 | I38: =IFERROR(SUMIF(Table3[Item ID],'Inventory calculations'!A38,Table3[Quantity]),0) -> 0 | J38: =IFERROR(SUMIF(Table4[Item ID],'Inventory calculations'!A38,Table4[Quantity Purchased]),0) -> 0 | K38: =H38+J38-I38 -> 1155 | L38: =IF(K38<0,"STOCK ISSUE","OK") -> OK | M38: =K38*E38 -> 1920972.9 | N38: =Table5[[#This Row],[Total Qty Sold]]*Table5[[#This Row],[Unit Price]] -> 0 | P38: =IF(Table5[[#This Row],[Last sale Date]]="","Never Sold",TODAY()-Table5[[#This Row],[Last sale Date]]) -> Never Sold | Q38: =IF(Table5[[#This Row],[Re order Level]]<=Table5[[#This Row],[Current stock]],"ORDERASAP","OK BUT BE CHECKING") -> OK BUT BE CHECKING | R38: =IF(AND(ISNUMBER(B38), B38 > 60), "DEAD", "ACTIVE") -> ACTIVE | S38: =IF(Table5[[#This Row],[DEADSTOCK FLAG]]="DEAD",Table5[[#This Row],[Inventory Value]],0) -> 0
A39: ='Inventory master'!A39 -> ITEM038-A | B39: ='Inventory master'!B39 -> 1x32 PLC Splitter | C39: ='Inventory master'!C39 -> Splitters | D39: ='Inventory master'!D39 -> AFL | E39: ='Inventory master'!E39 -> 1325.07 | F39: ='Inventory master'!F39 -> 2396.54 | G39: ='Inventory master'!G39 -> 47 | H39: =IFERROR(_xlfn.XLOOKUP(A39, 'Opening stock'!A39:A638, 'Opening stock'!E39:E638), "") -> 705 | I39: =IFERROR(SUMIF(Table3[Item ID],'Inventory calculations'!A39,Table3[Quantity]),0) -> 6 | J39: =IFERROR(SUMIF(Table4[Item ID],'Inventory calculations'!A39,Table4[Quantity Purchased]),0) -> 0 | K39: =H39+J39-I39 -> 699 | L39: =IF(K39<0,"STOCK ISSUE","OK") -> OK | M39: =K39*E39 -> 926223.93 | N39: =Table5[[#This Row],[Total Qty Sold]]*Table5[[#This Row],[Unit Price]] -> 14379.24 | O39: =IFERROR(_xlfn.MAXIFS(Table3[Date],Table3[Item ID],Table5[[#This Row],[Item ID]]),"") -> 45360 | P39: =IF(Table5[[#This Row],[Last sale Date]]="","Never Sold",TODAY()-Table5[[#This Row],[Last sale Date]]) -> 692 | Q39: =IF(Table5[[#This Row],[Re order Level]]<=Table5[[#This Row],[Current stock]],"ORDERASAP","OK BUT BE CHECKING") -> OK BUT BE CHECKING | R39: =IF(AND(ISNUMBER(B39), B39 > 60), "DEAD", "ACTIVE") -> ACTIVE | S39: =IF(Table5[[#This Row],[DEADSTOCK FLAG]]="DEAD",Table5[[#This Row],[Inventory Value]],0) -> 0
A40: ='Inventory master'!A40 -> ITEM039-A | B40: ='Inventory master'!B40 -> Fiber Optic Polisher | C40: ='Inventory master'!C40 -> Tools | D40: ='Inventory master'!D40 -> HellermannTyton | E40: ='Inventory master'!E40 -> 1828.15 | F40: ='Inventory master'!F40 -> 2159.76 | G40: ='Inventory master'!G40 -> 95 | H40: =IFERROR(_xlfn.XLOOKUP(A40, 'Opening stock'!A40:A639, 'Opening stock'!E40:E639), "") -> 1425 | I40: =IFERROR(SUMIF(Table3[Item ID],'Inventory calculations'!A40,Table3[Quantity]),0) -> 0 | J40: =IFERROR(SUMIF(Table4[Item ID],'Inventory calculations'!A40,Table4[Quantity Purchased]),0) -> 0 | K40: =H40+J40-I40 -> 1425 | L40: =IF(K40<0,"STOCK ISSUE","OK") -> OK | M40: =K40*E40 -> 2605113.8 | N40: =Table5[[#This Row],[Total Qty Sold]]*Table5[[#This Row],[Unit Price]] -> 0 | P40: =IF(Table5[[#This Row],[Last sale Date]]="","Never Sold",TODAY()-Table5[[#This Row],[Last sale Date]]) -> Never Sold | Q40: =IF(Table5[[#This Row],[Re order Level]]<=Table5[[#This Row],[Current stock]],"ORDERASAP","OK BUT BE CHECKING") -> OK BUT BE CHECKING | R40: =IF(AND(ISNUMBER(B40), B40 > 60), "DEAD", "ACTIVE") -> ACTIVE | S40: =IF(Table5[[#This Row],[DEADSTOCK FLAG]]="DEAD",Table5[[#This Row],[Inventory Value]],0) -> 0
A41: ='Inventory master'!A41 -> ITEM040-A | B41: ='Inventory master'!B41 -> Fiber Optic Polisher | C41: ='Inventory master'!C41 -> Tools | D41: ='Inventory master'!D41 -> HellermannTyton | E41: ='Inventory master'!E41 -> 1789.47 | F41: ='Inventory master'!F41 -> 3100.56 | G41: ='Inventory master'!G41 -> 84 | H41: =IFERROR(_xlfn.XLOOKUP(A41, 'Opening stock'!A41:A640, 'Opening stock'!E41:E640), "") -> 1260 | I41: =IFERROR(SUMIF(Table3[Item ID],'Inventory calculations'!A41,Table3[Quantity]),0) -> 0 | J41: =IFERROR(SUMIF(Table4[Item ID],'Inventory calculations'!A41,Table4[Quantity Purchased]),0) -> 4 | K41: =H41+J41-I41 -> 1264 | L41: =IF(K41<0,"STOCK ISSUE","OK") -> OK | M41: =K41*E41 -> 2261890.1 | N41: =Table5[[#This Row],[Total Qty Sold]]*Table5[[#This Row],[Unit Price]] -> 0 | P41: =IF(Table5[[#This Row],[Last sale Date]]="","Never Sold",TODAY()-Table5[[#This Row],[Last sale Date]]) -> Never Sold | Q41: =IF(Table5[[#This Row],[Re order Level]]<=Table5[[#This Row],[Current stock]],"ORDERASAP","OK BUT BE CHECKING") -> OK BUT BE CHECKING | R41: =IF(AND(ISNUMBER(B41), B41 > 60), "DEAD", "ACTIVE") -> ACTIVE | S41: =IF(Table5[[#This Row],[DEADSTOCK FLAG]]="DEAD",Table5[[#This Row],[Inventory Value]],0) -> 0
A42: ='Inventory master'!A42 -> ITEM041-A | B42: ='Inventory master'!B42 -> Fusion Splicer | C42: ='Inventory master'!C42 -> Splicers | D42: ='Inventory master'!D42 -> Panduit | E42: ='Inventory master'!E42 -> 237.27 | F42: ='Inventory master'!F42 -> 275.62 | G42: ='Inventory master'!G42 -> 85 | H42: =IFERROR(_xlfn.XLOOKUP(A42, 'Opening stock'!A42:A641, 'Opening stock'!E42:E641), "") -> 1275 | I42: =IFERROR(SUMIF(Table3[Item ID],'Inventory calculations'!A42,Table3[Quantity]),0) -> 0 | J42: =IFERROR(SUMIF(Table4[Item ID],'Inventory calculations'!A42,Table4[Quantity Purchased]),0) -> 21 | K42: =H42+J42-I42 -> 1296 | L42: =IF(K42<0,"STOCK ISSUE","OK") -> OK | M42: =K42*E42 -> 307501.92 | N42: =Table5[[#This Row],[Total Qty Sold]]*Table5[[#This Row],[Unit Price]] -> 0 | P42: =IF(Table5[[#This Row],[Last sale Date]]="","Never Sold",TODAY()-Table5[[#This Row],[Last sale Date]]) -> Never Sold | Q42: =IF(Table5[[#This Row],[Re order Level]]<=Table5[[#This Row],[Current stock]],"ORDERASAP","OK BUT BE CHECKING") -> OK BUT BE CHECKING | R42: =IF(AND(ISNUMBER(B42), B42 > 60), "DEAD", "ACTIVE") -> ACTIVE | S42: =IF(Table5[[#This Row],[DEADSTOCK FLAG]]="DEAD",Table5[[#This Row],[Inventory Value]],0) -> 0
A43: ='Inventory master'!A43 -> ITEM042-A | B43: ='Inventory master'!B43 -> ST UPC Connector | C43: ='Inventory master'!C43 -> Connectors | D43: ='Inventory master'!D43 -> Huber+Suhner | E43: ='Inventory master'!E43 -> 52.07 | F43: ='Inventory master'!F43 -> 76.97 | G43: ='Inventory master'!G43 -> 47 | H43: =IFERROR(_xlfn.XLOOKUP(A43, 'Opening stock'!A43:A642, 'Opening stock'!E43:E642), "") -> 705 | I43: =IFERROR(SUMIF(Table3[Item ID],'Inventory calculations'!A43,Table3[Quantity]),0) -> 0 | J43: =IFERROR(SUMIF(Table4[Item ID],'Inventory calculations'!A43,Table4[Quantity Purchased]),0) -> 10 | K43: =H43+J43-I43 -> 715 | L43: =IF(K43<0,"STOCK ISSUE","OK") -> OK | M43: =K43*E43 -> 37230.05 | N43: =Table5[[#This Row],[Total Qty Sold]]*Table5[[#This Row],[Unit Price]] -> 0 | P43: =IF(Table5[[#This Row],[Last sale Date]]="","Never Sold",TODAY()-Table5[[#This Row],[Last sale Date]]) -> Never Sold | Q43: =IF(Table5[[#This Row],[Re order Level]]<=Table5[[#This Row],[Current stock]],"ORDERASAP","OK BUT BE CHECKING") -> OK BUT BE CHECKING | R43: =IF(AND(ISNUMBER(B43), B43 > 60), "DEAD", "ACTIVE") -> ACTIVE | S43: =IF(Table5[[#This Row],[DEADSTOCK FLAG]]="DEAD",Table5[[#This Row],[Inventory Value]],0) -> 0
A44: ='Inventory master'!A44 -> ITEM043-A | B44: ='Inventory master'!B44 -> Pedestal Enclosure | C44: ='Inventory master'!C44 -> Enclosures | D44: ='Inventory master'!D44 -> CommScope | E44: ='Inventory master'!E44 -> 423.32 | F44: ='Inventory master'!F44 -> 611.2 | G44: ='Inventory master'!G44 -> 71 | H44: =IFERROR(_xlfn.XLOOKUP(A44, 'Opening stock'!A44:A643, 'Opening stock'!E44:E643), "") -> 1065 | I44: =IFERROR(SUMIF(Table3[Item ID],'Inventory calculations'!A44,Table3[Quantity]),0) -> 0 | J44: =IFERROR(SUMIF(Table4[Item ID],'Inventory calculations'!A44,Table4[Quantity Purchased]),0) -> 8 | K44: =H44+J44-I44 -> 1073 | L44: =IF(K44<0,"STOCK ISSUE","OK") -> OK | M44: =K44*E44 -> 454222.36 | N44: =Table5[[#This Row],[Total Qty Sold]]*Table5[[#This Row],[Unit Price]] -> 0 | P44: =IF(Table5[[#This Row],[Last sale Date]]="","Never Sold",TODAY()-Table5[[#This Row],[Last sale Date]]) -> Never Sold | Q44: =IF(Table5[[#This Row],[Re order Level]]<=Table5[[#This Row],[Current stock]],"ORDERASAP","OK BUT BE CHECKING") -> OK BUT BE CHECKING | R44: =IF(AND(ISNUMBER(B44), B44 > 60), "DEAD", "ACTIVE") -> ACTIVE | S44: =IF(Table5[[#This Row],[DEADSTOCK FLAG]]="DEAD",Table5[[#This Row],[Inventory Value]],0) -> 0
A45: ='Inventory master'!A45 -> ITEM044-A | B45: ='Inventory master'!B45 -> Fiber Optic Cutter | C45: ='Inventory master'!C45 -> Tools | D45: ='Inventory master'!D45 -> Amphenol | E45: ='Inventory master'!E45 -> 1153.06 | F45: ='Inventory master'!F45 -> 1402.0 | G45: ='Inventory master'!G45 -> 77 | H45: =IFERROR(_xlfn.XLOOKUP(A45, 'Opening stock'!A45:A644, 'Opening stock'!E45:E644), "") -> 1155 | I45: =IFERROR(SUMIF(Table3[Item ID],'Inventory calculations'!A45,Table3[Quantity]),0) -> 0 | J45: =IFERROR(SUMIF(Table4[Item ID],'Inventory calculations'!A45,Table4[Quantity Purchased]),0) -> 4 | K45: =H45+J45-I45 -> 1159 | L45: =IF(K45<0,"STOCK ISSUE","OK") -> OK | M45: =K45*E45 -> 1336396.5 | N45: =Table5[[#This Row],[Total Qty Sold]]*Table5[[#This Row],[Unit Price]] -> 0 | P45: =IF(Table5[[#This Row],[Last sale Date]]="","Never Sold",TODAY()-Table5[[#This Row],[Last sale Date]]) -> Never Sold | Q45: =IF(Table5[[#This Row],[Re order Level]]<=Table5[[#This Row],[Current stock]],"ORDERASAP","OK BUT BE CHECKING") -> OK BUT BE CHECKING | R45: =IF(AND(ISNUMBER(B45), B45 > 60), "DEAD", "ACTIVE") -> ACTIVE | S45: =IF(Table5[[#This Row],[DEADSTOCK FLAG]]="DEAD",Table5[[#This Row],[Inventory Value]],0) -> 0
A46: ='Inventory master'!A46 -> ITEM045-A | B46: ='Inventory master'!B46 -> Single-Mode Fiber Cable 100m | C46: ='Inventory master'!C46 -> Fiber Optic Cables | D46: ='Inventory master'!D46 -> TE Connectivity | E46: ='Inventory master'!E46 -> 422.48 | F46: ='Inventory master'!F46 -> 786.86 | G46: ='Inventory master'!G46 -> 76 | H46: =IFERROR(_xlfn.XLOOKUP(A46, 'Opening stock'!A46:A645, 'Opening stock'!E46:E645), "") -> 1140 | I46: =IFERROR(SUMIF(Table3[Item ID],'Inventory calculations'!A46,Table3[Quantity]),0) -> 0 | J46: =IFERROR(SUMIF(Table4[Item ID],'Inventory calculations'!A46,Table4[Quantity Purchased]),0) -> 20 | K46: =H46+J46-I46 -> 1160 | L46: =IF(K46<0,"STOCK ISSUE","OK") -> OK | M46: =K46*E46 -> 490076.8 | N46: =Table5[[#This Row],[Total Qty Sold]]*Table5[[#This Row],[Unit Price]] -> 0 | P46: =IF(Table5[[#This Row],[Last sale Date]]="","Never Sold",TODAY()-Table5[[#This Row],[Last sale Date]]) -> Never Sold | Q46: =IF(Table5[[#This Row],[Re order Level]]<=Table5[[#This Row],[Current stock]],"ORDERASAP","OK BUT BE CHECKING") -> OK BUT BE CHECKING | R46: =IF(AND(ISNUMBER(B46), B46 > 60), "DEAD", "ACTIVE") -> ACTIVE | S46: =IF(Table5[[#This Row],[DEADSTOCK FLAG]]="DEAD",Table5[[#This Row],[Inventory Value]],0) -> 0
A47: ='Inventory master'!A47 -> ITEM046-A | B47: ='Inventory master'!B47 -> Mechanical Splicer | C47: ='Inventory master'!C47 -> Splicers | D47: ='Inventory master'!D47 -> AFL | E47: ='Inventory master'!E47 -> 1063.44 | F47: ='Inventory master'!F47 -> 1887.12 | G47: ='Inventory master'!G47 -> 31 | H47: =IFERROR(_xlfn.XLOOKUP(A47, 'Opening stock'!A47:A646, 'Opening stock'!E47:E646), "") -> 465 | I47: =IFERROR(SUMIF(Table3[Item ID],'Inventory calculations'!A47,Table3[Quantity]),0) -> 5 | J47: =IFERROR(SUMIF(Table4[Item ID],'Inventory calculations'!A47,Table4[Quantity Purchased]),0) -> 0 | K47: =H47+J47-I47 -> 460 | L47: =IF(K47<0,"STOCK ISSUE","OK") -> OK | M47: =K47*E47 -> 489182.4 | N47: =Table5[[#This Row],[Total Qty Sold]]*Table5[[#This Row],[Unit Price]] -> 9435.6 | O47: =IFERROR(_xlfn.MAXIFS(Table3[Date],Table3[Item ID],Table5[[#This Row],[Item ID]]),"") -> 45476 | P47: =IF(Table5[[#This Row],[Last sale Date]]="","Never Sold",TODAY()-Table5[[#This Row],[Last sale Date]]) -> 576 | Q47: =IF(Table5[[#This Row],[Re order Level]]<=Table5[[#This Row],[Current stock]],"ORDERASAP","OK BUT BE CHECKING") -> OK BUT BE CHECKING | R47: =IF(AND(ISNUMBER(B47), B47 > 60), "DEAD", "ACTIVE") -> ACTIVE | S47: =IF(Table5[[#This Row],[DEADSTOCK FLAG]]="DEAD",Table5[[#This Row],[Inventory Value]],0) -> 0
A48: ='Inventory master'!A48 -> ITEM047-A | B48: ='Inventory master'!B48 -> QSFP28 Transceiver | C48: ='Inventory master'!C48 -> Transceivers | D48: ='Inventory master'!D48 -> HellermannTyton | E48: ='Inventory master'!E48 -> 1460.91 | F48: ='Inventory master'!F48 -> 1969.33 | G48: ='Inventory master'!G48 -> 67 | H48: =IFERROR(_xlfn.XLOOKUP(A48, 'Opening stock'!A48:A647, 'Opening stock'!E48:E647), "") -> 1005 | I48: =IFERROR(SUMIF(Table3[Item ID],'Inventory calculations'!A48,Table3[Quantity]),0) -> 0 | J48: =IFERROR(SUMIF(Table4[Item ID],'Inventory calculations'!A48,Table4[Quantity Purchased]),0) -> 2 | K48: =H48+J48-I48 -> 1007 | L48: =IF(K48<0,"STOCK ISSUE","OK") -> OK | M48: =K48*E48 -> 1471136.4 | N48: =Table5[[#This Row],[Total Qty Sold]]*Table5[[#This Row],[Unit Price]] -> 0 | P48: =IF(Table5[[#This Row],[Last sale Date]]="","Never Sold",TODAY()-Table5[[#This Row],[Last sale Date]]) -> Never Sold | Q48: =IF(Table5[[#This Row],[Re order Level]]<=Table5[[#This Row],[Current stock]],"ORDERASAP","OK BUT BE CHECKING") -> OK BUT BE CHECKING | R48: =IF(AND(ISNUMBER(B48), B48 > 60), "DEAD", "ACTIVE") -> ACTIVE | S48: =IF(Table5[[#This Row],[DEADSTOCK FLAG]]="DEAD",Table5[[#This Row],[Inventory Value]],0) -> 0
A49: ='Inventory master'!A49 -> ITEM048-A | B49: ='Inventory master'!B49 -> Outdoor Fiber Cable 50m | C49: ='Inventory master'!C49 -> Fiber Optic Cables | D49: ='Inventory master'!D49 -> Leviton | E49: ='Inventory master'!E49 -> 608.56 | F49: ='Inventory master'!F49 -> 1081.79 | G49: ='Inventory master'!G49 -> 17 | H49: =IFERROR(_xlfn.XLOOKUP(A49, 'Opening stock'!A49:A648, 'Opening stock'!E49:E648), "") -> 255 | I49: =IFERROR(SUMIF(Table3[Item ID],'Inventory calculations'!A49,Table3[Quantity]),0) -> 0 | J49: =IFERROR(SUMIF(Table4[Item ID],'Inventory calculations'!A49,Table4[Quantity Purchased]),0) -> 0 | K49: =H49+J49-I49 -> 255 | L49: =IF(K49<0,"STOCK ISSUE","OK") -> OK | M49: =K49*E49 -> 155182.8 | N49: =Table5[[#This Row],[Total Qty Sold]]*Table5[[#This Row],[Unit Price]] -> 0 | P49: =IF(Table5[[#This Row],[Last sale Date]]="","Never Sold",TODAY()-Table5[[#This Row],[Last sale Date]]) -> Never Sold | Q49: =IF(Table5[[#This Row],[Re order Level]]<=Table5[[#This Row],[Current stock]],"ORDERASAP","OK BUT BE CHECKING") -> OK BUT BE CHECKING | R49: =IF(AND(ISNUMBER(B49), B49 > 60), "DEAD", "ACTIVE") -> ACTIVE | S49: =IF(Table5[[#This Row],[DEADSTOCK FLAG]]="DEAD",Table5[[#This Row],[Inventory Value]],0) -> 0
A50: ='Inventory master'!A50 -> ITEM049-A | B50: ='Inventory master'!B50 -> Fusion Splicer | C50: ='Inventory master'!C50 -> Splicers | D50: ='Inventory master'!D50 -> HellermannTyton | E50: ='Inventory master'!E50 -> 1063.5 | F50: ='Inventory master'!F50 -> 1564.29 | G50: ='Inventory master'!G50 -> 54 | H50: =IFERROR(_xlfn.XLOOKUP(A50, 'Opening stock'!A50:A649, 'Opening stock'!E50:E649), "") -> 810 | I50: =IFERROR(SUMIF(Table3[Item ID],'Inventory calculations'!A50,Table3[Quantity]),0) -> 0 | J50: =IFERROR(SUMIF(Table4[Item ID],'Inventory calculations'!A50,Table4[Quantity Purchased]),0) -> 29 | K50: =H50+J50-I50 -> 839 | L50: =IF(K50<0,"STOCK ISSUE","OK") -> OK | M50: =K50*E50 -> 892276.5 | N50: =Table5[[#This Row],[Total Qty Sold]]*Table5[[#This Row],[Unit Price]] -> 0 | P50: =IF(Table5[[#This Row],[Last sale Date]]="","Never Sold",TODAY()-Table5[[#This Row],[Last sale Date]]) -> Never Sold | Q50: =IF(Table5[[#This Row],[Re order Level]]<=Table5[[#This Row],[Current stock]],"ORDERASAP","OK BUT BE CHECKING") -> OK BUT BE CHECKING | R50: =IF(AND(ISNUMBER(B50), B50 > 60), "DEAD", "ACTIVE") -> ACTIVE | S50: =IF(Table5[[#This Row],[DEADSTOCK FLAG]]="DEAD",Table5[[#This Row],[Inventory Value]],0) -> 0
A51: ='Inventory master'!A51 -> ITEM050-A | B51: ='Inventory master'!B51 -> QSFP Transceiver | C51: ='Inventory master'!C51 -> Transceivers | D51: ='Inventory master'!D51 -> Amphenol | E51: ='Inventory master'!E51 -> 601.09 | F51: ='Inventory master'!F51 -> 950.25 | G51: ='Inventory master'!G51 -> 66 | H51: =IFERROR(_xlfn.XLOOKUP(A51, 'Opening stock'!A51:A650, 'Opening stock'!E51:E650), "") -> 990 | I51: =IFERROR(SUMIF(Table3[Item ID],'Inventory calculations'!A51,Table3[Quantity]),0) -> 0 | J51: =IFERROR(SUMIF(Table4[Item ID],'Inventory calculations'!A51,Table4[Quantity Purchased]),0) -> 0 | K51: =H51+J51-I51 -> 990 | L51: =IF(K51<0,"STOCK ISSUE","OK") -> OK | M51: =K51*E51 -> 595079.1 | N51: =Table5[[#This Row],[Total Qty Sold]]*Table5[[#This Row],[Unit Price]] -> 0 | P51: =IF(Table5[[#This Row],[Last sale Date]]="","Never Sold",TODAY()-Table5[[#This Row],[Last sale Date]]) -> Never Sold | Q51: =IF(Table5[[#This Row],[Re order Level]]<=Table5[[#This Row],[Current stock]],"ORDERASAP","OK BUT BE CHECKING") -> OK BUT BE CHECKING | R51: =IF(AND(ISNUMBER(B51), B51 > 60), "DEAD", "ACTIVE") -> ACTIVE | S51: =IF(Table5[[#This Row],[DEADSTOCK FLAG]]="DEAD",Table5[[#This Row],[Inventory Value]],0) -> 0
A52: ='Inventory master'!A52 -> ITEM051-A | B52: ='Inventory master'!B52 -> QSFP28 Transceiver | C52: ='Inventory master'!C52 -> Transceivers | D52: ='Inventory master'!D52 -> HellermannTyton | E52: ='Inventory master'!E52 -> 1619.64 | F52: ='Inventory master'!F52 -> 2597.35 | G52: ='Inventory master'!G52 -> 63 | H52: =IFERROR(_xlfn.XLOOKUP(A52, 'Opening stock'!A52:A651, 'Opening stock'!E52:E651), "") -> 945 | I52: =IFERROR(SUMIF(Table3[Item ID],'Inventory calculations'!A52,Table3[Quantity]),0) -> 0 | J52: =IFERROR(SUMIF(Table4[Item ID],'Inventory calculations'!A52,Table4[Quantity Purchased]),0) -> 16 | K52: =H52+J52-I52 -> 961 | L52: =IF(K52<0,"STOCK ISSUE","OK") -> OK | M52: =K52*E52 -> 1556474 | N52: =Table5[[#This Row],[Total Qty Sold]]*Table5[[#This Row],[Unit Price]] -> 0 | P52: =IF(Table5[[#This Row],[Last sale Date]]="","Never Sold",TODAY()-Table5[[#This Row],[Last sale Date]]) -> Never Sold | Q52: =IF(Table5[[#This Row],[Re order Level]]<=Table5[[#This Row],[Current stock]],"ORDERASAP","OK BUT BE CHECKING") -> OK BUT BE CHECKING | R52: =IF(AND(ISNUMBER(B52), B52 > 60), "DEAD", "ACTIVE") -> ACTIVE | S52: =IF(Table5[[#This Row],[DEADSTOCK FLAG]]="DEAD",Table5[[#This Row],[Inventory Value]],0) -> 0
A53: ='Inventory master'!A53 -> ITEM052-A | B53: ='Inventory master'!B53 -> Single-Mode Fiber Cable 200m | C53: ='Inventory master'!C53 -> Fiber Optic Cables | D53: ='Inventory master'!D53 -> Leviton | E53: ='Inventory master'!E53 -> 1985.84 | F53: ='Inventory master'!F53 -> 2298.88 | G53: ='Inventory master'!G53 -> 16 | H53: =IFERROR(_xlfn.XLOOKUP(A53, 'Opening stock'!A53:A652, 'Opening stock'!E53:E652), "") -> 240 | I53: =IFERROR(SUMIF(Table3[Item ID],'Inventory calculations'!A53,Table3[Quantity]),0) -> 13 | J53: =IFERROR(SUMIF(Table4[Item ID],'Inventory calculations'!A53,Table4[Quantity Purchased]),0) -> 6 | K53: =H53+J53-I53 -> 233 | L53: =IF(K53<0,"STOCK ISSUE","OK") -> OK | M53: =K53*E53 -> 462700.72 | N53: =Table5[[#This Row],[Total Qty Sold]]*Table5[[#This Row],[Unit Price]] -> 29885.44 | O53: =IFERROR(_xlfn.MAXIFS(Table3[Date],Table3[Item ID],Table5[[#This Row],[Item ID]]),"") -> 45377 | P53: =IF(Table5[[#This Row],[Last sale Date]]="","Never Sold",TODAY()-Table5[[#This Row],[Last sale Date]]) -> 675 | Q53: =IF(Table5[[#This Row],[Re order Level]]<=Table5[[#This Row],[Current stock]],"ORDERASAP","OK BUT BE CHECKING") -> OK BUT BE CHECKING | R53: =IF(AND(ISNUMBER(B53), B53 > 60), "DEAD", "ACTIVE") -> ACTIVE | S53: =IF(Table5[[#This Row],[DEADSTOCK FLAG]]="DEAD",Table5[[#This Row],[Inventory Value]],0) -> 0
A54: ='Inventory master'!A54 -> ITEM053-A | B54: ='Inventory master'!B54 -> 1x8 PLC Splitter | C54: ='Inventory master'!C54 -> Splitters | D54: ='Inventory master'!D54 -> Huber+Suhner | E54: ='Inventory master'!E54 -> 589.26 | F54: ='Inventory master'!F54 -> 1169.4 | G54: ='Inventory master'!G54 -> 83 | H54: =IFERROR(_xlfn.XLOOKUP(A54, 'Opening stock'!A54:A653, 'Opening stock'!E54:E653), "") -> 1245 | I54: =IFERROR(SUMIF(Table3[Item ID],'Inventory calculations'!A54,Table3[Quantity]),0) -> 0 | J54: =IFERROR(SUMIF(Table4[Item ID],'Inventory calculations'!A54,Table4[Quantity Purchased]),0) -> 23 | K54: =H54+J54-I54 -> 1268 | L54: =IF(K54<0,"STOCK ISSUE","OK") -> OK | M54: =K54*E54 -> 747181.68 | N54: =Table5[[#This Row],[Total Qty Sold]]*Table5[[#This Row],[Unit Price]] -> 0 | P54: =IF(Table5[[#This Row],[Last sale Date]]="","Never Sold",TODAY()-Table5[[#This Row],[Last sale Date]]) -> Never Sold | Q54: =IF(Table5[[#This Row],[Re order Level]]<=Table5[[#This Row],[Current stock]],"ORDERASAP","OK BUT BE CHECKING") -> OK BUT BE CHECKING | R54: =IF(AND(ISNUMBER(B54), B54 > 60), "DEAD", "ACTIVE") -> ACTIVE | S54: =IF(Table5[[#This Row],[DEADSTOCK FLAG]]="DEAD",Table5[[#This Row],[Inventory Value]],0) -> 0
A55: ='Inventory master'!A55 -> ITEM054-A | B55: ='Inventory master'!B55 -> Fiber Optic Stripper | C55: ='Inventory master'!C55 -> Tools | D55: ='Inventory master'!D55 -> Prysmian Group | E55: ='Inventory master'!E55 -> 217.34 | F55: ='Inventory master'!F55 -> 344.64 | G55: ='Inventory master'!G55 -> 56 | H55: =IFERROR(_xlfn.XLOOKUP(A55, 'Opening stock'!A55:A654, 'Opening stock'!E55:E654), "") -> 840 | I55: =IFERROR(SUMIF(Table3[Item ID],'Inventory calculations'!A55,Table3[Quantity]),0) -> 0 | J55: =IFERROR(SUMIF(Table4[Item ID],'Inventory calculations'!A55,Table4[Quantity Purchased]),0) -> 11 | K55: =H55+J55-I55 -> 851 | L55: =IF(K55<0,"STOCK ISSUE","OK") -> OK | M55: =K55*E55 -> 184956.34 | N55: =Table5[[#This Row],[Total Qty Sold]]*Table5[[#This Row],[Unit Price]] -> 0 | P55: =IF(Table5[[#This Row],[Last sale Date]]="","Never Sold",TODAY()-Table5[[#This Row],[Last sale Date]]) -> Never Sold | Q55: =IF(Table5[[#This Row],[Re order Level]]<=Table5[[#This Row],[Current stock]],"ORDERASAP","OK BUT BE CHECKING") -> OK BUT BE CHECKING | R55: =IF(AND(ISNUMBER(B55), B55 > 60), "DEAD", "ACTIVE") -> ACTIVE | S55: =IF(Table5[[#This Row],[DEADSTOCK FLAG]]="DEAD",Table5[[#This Row],[Inventory Value]],0) -> 0
A56: ='Inventory master'!A56 -> ITEM055-A | B56: ='Inventory master'!B56 -> Mechanical Splicer | C56: ='Inventory master'!C56 -> Splicers | D56: ='Inventory master'!D56 -> Amphenol | E56: ='Inventory master'!E56 -> 378.73 | F56: ='Inventory master'!F56 -> 731.32 | G56: ='Inventory master'!G56 -> 70 | H56: =IFERROR(_xlfn.XLOOKUP(A56, 'Opening stock'!A56:A655, 'Opening stock'!E56:E655), "") -> 1050 | I56: =IFERROR(SUMIF(Table3[Item ID],'Inventory calculations'!A56,Table3[Quantity]),0) -> 0 | J56: =IFERROR(SUMIF(Table4[Item ID],'Inventory calculations'!A56,Table4[Quantity Purchased]),0) -> 2 | K56: =H56+J56-I56 -> 1052 | L56: =IF(K56<0,"STOCK ISSUE","OK") -> OK | M56: =K56*E56 -> 398423.96 | N56: =Table5[[#This Row],[Total Qty Sold]]*Table5[[#This Row],[Unit Price]] -> 0 | P56: =IF(Table5[[#This Row],[Last sale Date]]="","Never Sold",TODAY()-Table5[[#This Row],[Last sale Date]]) -> Never Sold | Q56: =IF(Table5[[#This Row],[Re order Level]]<=Table5[[#This Row],[Current stock]],"ORDERASAP","OK BUT BE CHECKING") -> OK BUT BE CHECKING | R56: =IF(AND(ISNUMBER(B56), B56 > 60), "DEAD", "ACTIVE") -> ACTIVE | S56: =IF(Table5[[#This Row],[DEADSTOCK FLAG]]="DEAD",Table5[[#This Row],[Inventory Value]],0) -> 0
A57: ='Inventory master'!A57 -> ITEM056-A | B57: ='Inventory master'!B57 -> Mechanical Splicer | C57: ='Inventory master'!C57 -> Splicers | D57: ='Inventory master'!D57 -> HellermannTyton | E57: ='Inventory master'!E57 -> 749.97 | F57: ='Inventory master'!F57 -> 1424.65 | G57: ='Inventory master'!G57 -> 11 | H57: =IFERROR(_xlfn.XLOOKUP(A57, 'Opening stock'!A57:A656, 'Opening stock'!E57:E656), "") -> 165 | I57: =IFERROR(SUMIF(Table3[Item ID],'Inventory calculations'!A57,Table3[Quantity]),0) -> 0 | J57: =IFERROR(SUMIF(Table4[Item ID],'Inventory calculations'!A57,Table4[Quantity Purchased]),0) -> 14 | K57: =H57+J57-I57 -> 179 | L57: =IF(K57<0,"STOCK ISSUE","OK") -> OK | M57: =K57*E57 -> 134244.63 | N57: =Table5[[#This Row],[Total Qty Sold]]*Table5[[#This Row],[Unit Price]] -> 0 | P57: =IF(Table5[[#This Row],[Last sale Date]]="","Never Sold",TODAY()-Table5[[#This Row],[Last sale Date]]) -> Never Sold | Q57: =IF(Table5[[#This Row],[Re order Level]]<=Table5[[#This Row],[Current stock]],"ORDERASAP","OK BUT BE CHECKING") -> OK BUT BE CHECKING | R57: =IF(AND(ISNUMBER(B57), B57 > 60), "DEAD", "ACTIVE") -> ACTIVE | S57: =IF(Table5[[#This Row],[DEADSTOCK FLAG]]="DEAD",Table5[[#This Row],[Inventory Value]],0) -> 0
A58: ='Inventory master'!A58 -> ITEM057-A | B58: ='Inventory master'!B58 -> Fiber Jumper | C58: ='Inventory master'!C58 -> Accessories | D58: ='Inventory master'!D58 -> Prysmian Group | E58: ='Inventory master'!E58 -> 1581.53 | F58: ='Inventory master'!F58 -> 2927.58 | G58: ='Inventory master'!G58 -> 94 | H58: =IFERROR(_xlfn.XLOOKUP(A58, 'Opening stock'!A58:A657, 'Opening stock'!E58:E657), "") -> 1410 | I58: =IFERROR(SUMIF(Table3[Item ID],'Inventory calculations'!A58,Table3[Quantity]),0) -> 0 | J58: =IFERROR(SUMIF(Table4[Item ID],'Inventory calculations'!A58,Table4[Quantity Purchased]),0) -> 1 | K58: =H58+J58-I58 -> 1411 | L58: =IF(K58<0,"STOCK ISSUE","OK") -> OK | M58: =K58*E58 -> 2231538.8 | N58: =Table5[[#This Row],[Total Qty Sold]]*Table5[[#This Row],[Unit Price]] -> 0 | P58: =IF(Table5[[#This Row],[Last sale Date]]="","Never Sold",TODAY()-Table5[[#This Row],[Last sale Date]]) -> Never Sold | Q58: =IF(Table5[[#This Row],[Re order Level]]<=Table5[[#This Row],[Current stock]],"ORDERASAP","OK BUT BE CHECKING") -> OK BUT BE CHECKING | R58: =IF(AND(ISNUMBER(B58), B58 > 60), "DEAD", "ACTIVE") -> ACTIVE | S58: =IF(Table5[[#This Row],[DEADSTOCK FLAG]]="DEAD",Table5[[#This Row],[Inventory Value]],0) -> 0
A59: ='Inventory master'!A59 -> ITEM058-A | B59: ='Inventory master'!B59 -> MPO APC Connector | C59: ='Inventory master'!C59 -> Connectors | D59: ='Inventory master'!D59 -> CommScope | E59: ='Inventory master'!E59 -> 260.34 | F59: ='Inventory master'!F59 -> 289.51 | G59: ='Inventory master'!G59 -> 36 | H59: =IFERROR(_xlfn.XLOOKUP(A59, 'Opening stock'!A59:A658, 'Opening stock'!E59:E658), "") -> 540 | I59: =IFERROR(SUMIF(Table3[Item ID],'Inventory calculations'!A59,Table3[Quantity]),0) -> 0 | J59: =IFERROR(SUMIF(Table4[Item ID],'Inventory calculations'!A59,Table4[Quantity Purchased]),0) -> 2 | K59: =H59+J59-I59 -> 542 | L59: =IF(K59<0,"STOCK ISSUE","OK") -> OK | M59: =K59*E59 -> 141104.28 | N59: =Table5[[#This Row],[Total Qty Sold]]*Table5[[#This Row],[Unit Price]] -> 0 | P59: =IF(Table5[[#This Row],[Last sale Date]]="","Never Sold",TODAY()-Table5[[#This Row],[Last sale Date]]) -> Never Sold | Q59: =IF(Table5[[#This Row],[Re order Level]]<=Table5[[#This Row],[Current stock]],"ORDERASAP","OK BUT BE CHECKING") -> OK BUT BE CHECKING | R59: =IF(AND(ISNUMBER(B59), B59 > 60), "DEAD", "ACTIVE") -> ACTIVE | S59: =IF(Table5[[#This Row],[DEADSTOCK FLAG]]="DEAD",Table5[[#This Row],[Inventory Value]],0) -> 0
A60: ='Inventory master'!A60 -> ITEM059-A | B60: ='Inventory master'!B60 -> 12-Port Fiber Patch Panel | C60: ='Inventory master'!C60 -> Patch Panels | D60: ='Inventory master'!D60 -> Amphenol | E60: ='Inventory master'!E60 -> 333.48 | F60: ='Inventory master'!F60 -> 664.57 | G60: ='Inventory master'!G60 -> 24 | H60: =IFERROR(_xlfn.XLOOKUP(A60, 'Opening stock'!A60:A659, 'Opening stock'!E60:E659), "") -> 360 | I60: =IFERROR(SUMIF(Table3[Item ID],'Inventory calculations'!A60,Table3[Quantity]),0) -> 3 | J60: =IFERROR(SUMIF(Table4[Item ID],'Inventory calculations'!A60,Table4[Quantity Purchased]),0) -> 0 | K60: =H60+J60-I60 -> 357 | L60: =IF(K60<0,"STOCK ISSUE","OK") -> OK | M60: =K60*E60 -> 119052.36 | N60: =Table5[[#This Row],[Total Qty Sold]]*Table5[[#This Row],[Unit Price]] -> 1993.71 | O60: =IFERROR(_xlfn.MAXIFS(Table3[Date],Table3[Item ID],Table5[[#This Row],[Item ID]]),"") -> 45329 | P60: =IF(Table5[[#This Row],[Last sale Date]]="","Never Sold",TODAY()-Table5[[#This Row],[Last sale Date]]) -> 723 | Q60: =IF(Table5[[#This Row],[Re order Level]]<=Table5[[#This Row],[Current stock]],"ORDERASAP","OK BUT BE CHECKING") -> OK BUT BE CHECKING | R60: =IF(AND(ISNUMBER(B60), B60 > 60), "DEAD", "ACTIVE") -> ACTIVE | S60: =IF(Table5[[#This Row],[DEADSTOCK FLAG]]="DEAD",Table5[[#This Row],[Inventory Value]],0) -> 0
A61: ='Inventory master'!A61 -> ITEM060-A | B61: ='Inventory master'!B61 -> Fiber Optic Stripper | C61: ='Inventory master'!C61 -> Tools | D61: ='Inventory master'!D61 -> Huber+Suhner | E61: ='Inventory master'!E61 -> 1808.2 | F61: ='Inventory master'!F61 -> 3225.72 | G61: ='Inventory master'!G61 -> 79 | H61: =IFERROR(_xlfn.XLOOKUP(A61, 'Opening stock'!A61:A660, 'Opening stock'!E61:E660), "") -> 1185 | I61: =IFERROR(SUMIF(Table3[Item ID],'Inventory calculations'!A61,Table3[Quantity]),0) -> 0 | J61: =IFERROR(SUMIF(Table4[Item ID],'Inventory calculations'!A61,Table4[Quantity Purchased]),0) -> 6 | K61: =H61+J61-I61 -> 1191 | L61: =IF(K61<0,"STOCK ISSUE","OK") -> OK | M61: =K61*E61 -> 2153566.2 | N61: =Table5[[#This Row],[Total Qty Sold]]*Table5[[#This Row],[Unit Price]] -> 0 | P61: =IF(Table5[[#This Row],[Last sale Date]]="","Never Sold",TODAY()-Table5[[#This Row],[Last sale Date]]) -> Never Sold | Q61: =IF(Table5[[#This Row],[Re order Level]]<=Table5[[#This Row],[Current stock]],"ORDERASAP","OK BUT BE CHECKING") -> OK BUT BE CHECKING | R61: =IF(AND(ISNUMBER(B61), B61 > 60), "DEAD", "ACTIVE") -> ACTIVE | S61: =IF(Table5[[#This Row],[DEADSTOCK FLAG]]="DEAD",Table5[[#This Row],[Inventory Value]],0) -> 0
A62: ='Inventory master'!A62 -> ITEM061-A | B62: ='Inventory master'!B62 -> Single-Mode Fiber Cable 200m | C62: ='Inventory master'!C62 -> Fiber Optic Cables | D62: ='Inventory master'!D62 -> AFL | E62: ='Inventory master'!E62 -> 1757.54 | F62: ='Inventory master'!F62 -> 3028.11 | G62: ='Inventory master'!G62 -> 98 | H62: =IFERROR(_xlfn.XLOOKUP(A62, 'Opening stock'!A62:A661, 'Opening stock'!E62:E661), "") -> 1470 | I62: =IFERROR(SUMIF(Table3[Item ID],'Inventory calculations'!A62,Table3[Quantity]),0) -> 0 | J62: =IFERROR(SUMIF(Table4[Item ID],'Inventory calculations'!A62,Table4[Quantity Purchased]),0) -> 4 | K62: =H62+J62-I62 -> 1474 | L62: =IF(K62<0,"STOCK ISSUE","OK") -> OK | M62: =K62*E62 -> 2590614 | N62: =Table5[[#This Row],[Total Qty Sold]]*Table5[[#This Row],[Unit Price]] -> 0 | P62: =IF(Table5[[#This Row],[Last sale Date]]="","Never Sold",TODAY()-Table5[[#This Row],[Last sale Date]]) -> Never Sold | Q62: =IF(Table5[[#This Row],[Re order Level]]<=Table5[[#This Row],[Current stock]],"ORDERASAP","OK BUT BE CHECKING") -> OK BUT BE CHECKING | R62: =IF(AND(ISNUMBER(B62), B62 > 60), "DEAD", "ACTIVE") -> ACTIVE | S62: =IF(Table5[[#This Row],[DEADSTOCK FLAG]]="DEAD",Table5[[#This Row],[Inventory Value]],0) -> 0
A63: ='Inventory master'!A63 -> ITEM062-A | B63: ='Inventory master'!B63 -> Fiber Pigtail | C63: ='Inventory master'!C63 -> Accessories | D63: ='Inventory master'!D63 -> Prysmian Group | E63: ='Inventory master'!E63 -> 818.08 | F63: ='Inventory master'!F63 -> 1244.03 | G63: ='Inventory master'!G63 -> 10 | H63: =IFERROR(_xlfn.XLOOKUP(A63, 'Opening stock'!A63:A662, 'Opening stock'!E63:E662), "") -> 150 | I63: =IFERROR(SUMIF(Table3[Item ID],'Inventory calculations'!A63,Table3[Quantity]),0) -> 2 | J63: =IFERROR(SUMIF(Table4[Item ID],'Inventory calculations'!A63,Table4[Quantity Purchased]),0) -> 14 | K63: =H63+J63-I63 -> 162 | L63: =IF(K63<0,"STOCK ISSUE","OK") -> OK | M63: =K63*E63 -> 132528.96 | N63: =Table5[[#This Row],[Total Qty Sold]]*Table5[[#This Row],[Unit Price]] -> 2488.06 | O63: =IFERROR(_xlfn.MAXIFS(Table3[Date],Table3[Item ID],Table5[[#This Row],[Item ID]]),"") -> 45846 | P63: =IF(Table5[[#This Row],[Last sale Date]]="","Never Sold",TODAY()-Table5[[#This Row],[Last sale Date]]) -> 206 | Q63: =IF(Table5[[#This Row],[Re order Level]]<=Table5[[#This Row],[Current stock]],"ORDERASAP","OK BUT BE CHECKING") -> OK BUT BE CHECKING | R63: =IF(AND(ISNUMBER(B63), B63 > 60), "DEAD", "ACTIVE") -> ACTIVE | S63: =IF(Table5[[#This Row],[DEADSTOCK FLAG]]="DEAD",Table5[[#This Row],[Inventory Value]],0) -> 0
A64: ='Inventory master'!A64 -> ITEM063-A | B64: ='Inventory master'!B64 -> Fusion Splicer | C64: ='Inventory master'!C64 -> Splicers | D64: ='Inventory master'!D64 -> Huber+Suhner | E64: ='Inventory master'!E64 -> 1096.42 | F64: ='Inventory master'!F64 -> 1631.52 | G64: ='Inventory master'!G64 -> 52 | H64: =IFERROR(_xlfn.XLOOKUP(A64, 'Opening stock'!A64:A663, 'Opening stock'!E64:E663), "") -> 780 | I64: =IFERROR(SUMIF(Table3[Item ID],'Inventory calculations'!A64,Table3[Quantity]),0) -> 0 | J64: =IFERROR(SUMIF(Table4[Item ID],'Inventory calculations'!A64,Table4[Quantity Purchased]),0) -> 10 | K64: =H64+J64-I64 -> 790 | L64: =IF(K64<0,"STOCK ISSUE","OK") -> OK | M64: =K64*E64 -> 866171.8 | N64: =Table5[[#This Row],[Total Qty Sold]]*Table5[[#This Row],[Unit Price]] -> 0 | P64: =IF(Table5[[#This Row],[Last sale Date]]="","Never Sold",TODAY()-Table5[[#This Row],[Last sale Date]]) -> Never Sold | Q64: =IF(Table5[[#This Row],[Re order Level]]<=Table5[[#This Row],[Current stock]],"ORDERASAP","OK BUT BE CHECKING") -> OK BUT BE CHECKING | R64: =IF(AND(ISNUMBER(B64), B64 > 60), "DEAD", "ACTIVE") -> ACTIVE | S64: =IF(Table5[[#This Row],[DEADSTOCK FLAG]]="DEAD",Table5[[#This Row],[Inventory Value]],0) -> 0
A65: ='Inventory master'!A65 -> ITEM064-A | B65: ='Inventory master'!B65 -> CFP Transceiver | C65: ='Inventory master'!C65 -> Transceivers | D65: ='Inventory master'!D65 -> Huber+Suhner | E65: ='Inventory master'!E65 -> 275.74 | F65: ='Inventory master'!F65 -> 519.42 | G65: ='Inventory master'!G65 -> 96 | H65: =IFERROR(_xlfn.XLOOKUP(A65, 'Opening stock'!A65:A664, 'Opening stock'!E65:E664), "") -> 1440 | I65: =IFERROR(SUMIF(Table3[Item ID],'Inventory calculations'!A65,Table3[Quantity]),0) -> 0 | J65: =IFERROR(SUMIF(Table4[Item ID],'Inventory calculations'!A65,Table4[Quantity Purchased]),0) -> 0 | K65: =H65+J65-I65 -> 1440 | L65: =IF(K65<0,"STOCK ISSUE","OK") -> OK | M65: =K65*E65 -> 397065.6 | N65: =Table5[[#This Row],[Total Qty Sold]]*Table5[[#This Row],[Unit Price]] -> 0 | P65: =IF(Table5[[#This Row],[Last sale Date]]="","Never Sold",TODAY()-Table5[[#This Row],[Last sale Date]]) -> Never Sold | Q65: =IF(Table5[[#This Row],[Re order Level]]<=Table5[[#This Row],[Current stock]],"ORDERASAP","OK BUT BE CHECKING") -> OK BUT BE CHECKING | R65: =IF(AND(ISNUMBER(B65), B65 > 60), "DEAD", "ACTIVE") -> ACTIVE | S65: =IF(Table5[[#This Row],[DEADSTOCK FLAG]]="DEAD",Table5[[#This Row],[Inventory Value]],0) -> 0
A66: ='Inventory master'!A66 -> ITEM065-A | B66: ='Inventory master'!B66 -> LC UPC Connector | C66: ='Inventory master'!C66 -> Connectors | D66: ='Inventory master'!D66 -> CommScope | E66: ='Inventory master'!E66 -> 953.43 | F66: ='Inventory master'!F66 -> 1646.19 | G66: ='Inventory master'!G66 -> 46 | H66: =IFERROR(_xlfn.XLOOKUP(A66, 'Opening stock'!A66:A665, 'Opening stock'!E66:E665), "") -> 690 | I66: =IFERROR(SUMIF(Table3[Item ID],'Inventory calculations'!A66,Table3[Quantity]),0) -> 0 | J66: =IFERROR(SUMIF(Table4[Item ID],'Inventory calculations'!A66,Table4[Quantity Purchased]),0) -> 7 | K66: =H66+J66-I66 -> 697 | L66: =IF(K66<0,"STOCK ISSUE","OK") -> OK | M66: =K66*E66 -> 664540.71 | N66: =Table5[[#This Row],[Total Qty Sold]]*Table5[[#This Row],[Unit Price]] -> 0 | P66: =IF(Table5[[#This Row],[Last sale Date]]="","Never Sold",TODAY()-Table5[[#This Row],[Last sale Date]]) -> Never Sold | Q66: =IF(Table5[[#This Row],[Re order Level]]<=Table5[[#This Row],[Current stock]],"ORDERASAP","OK BUT BE CHECKING") -> OK BUT BE CHECKING | R66: =IF(AND(ISNUMBER(B66), B66 > 60), "DEAD", "ACTIVE") -> ACTIVE | S66: =IF(Table5[[#This Row],[DEADSTOCK FLAG]]="DEAD",Table5[[#This Row],[Inventory Value]],0) -> 0
A67: ='Inventory master'!A67 -> ITEM066-A | B67: ='Inventory master'!B67 -> Mechanical Splicer | C67: ='Inventory master'!C67 -> Splicers | D67: ='Inventory master'!D67 -> AFL | E67: ='Inventory master'!E67 -> 1131.74 | F67: ='Inventory master'!F67 -> 1549.72 | G67: ='Inventory master'!G67 -> 66 | H67: =IFERROR(_xlfn.XLOOKUP(A67, 'Opening stock'!A67:A666, 'Opening stock'!E67:E666), "") -> 990 | I67: =IFERROR(SUMIF(Table3[Item ID],'Inventory calculations'!A67,Table3[Quantity]),0) -> 0 | J67: =IFERROR(SUMIF(Table4[Item ID],'Inventory calculations'!A67,Table4[Quantity Purchased]),0) -> 12 | K67: =H67+J67-I67 -> 1002 | L67: =IF(K67<0,"STOCK ISSUE","OK") -> OK | M67: =K67*E67 -> 1134003.5 | N67: =Table5[[#This Row],[Total Qty Sold]]*Table5[[#This Row],[Unit Price]] -> 0 | P67: =IF(Table5[[#This Row],[Last sale Date]]="","Never Sold",TODAY()-Table5[[#This Row],[Last sale Date]]) -> Never Sold | Q67: =IF(Table5[[#This Row],[Re order Level]]<=Table5[[#This Row],[Current stock]],"ORDERASAP","OK BUT BE CHECKING") -> OK BUT BE CHECKING | R67: =IF(AND(ISNUMBER(B67), B67 > 60), "DEAD", "ACTIVE") -> ACTIVE | S67: =IF(Table5[[#This Row],[DEADSTOCK FLAG]]="DEAD",Table5[[#This Row],[Inventory Value]],0) -> 0
A68: ='Inventory master'!A68 -> ITEM067-A | B68: ='Inventory master'!B68 -> Fiber Optic Tester | C68: ='Inventory master'!C68 -> Tools | D68: ='Inventory master'!D68 -> CommScope | E68: ='Inventory master'!E68 -> 1280.05 | F68: ='Inventory master'!F68 -> 1966.77 | G68: ='Inventory master'!G68 -> 98 | H68: =IFERROR(_xlfn.XLOOKUP(A68, 'Opening stock'!A68:A667, 'Opening stock'!E68:E667), "") -> 1470 | I68: =IFERROR(SUMIF(Table3[Item ID],'Inventory calculations'!A68,Table3[Quantity]),0) -> 12 | J68: =IFERROR(SUMIF(Table4[Item ID],'Inventory calculations'!A68,Table4[Quantity Purchased]),0) -> 0 | K68: =H68+J68-I68 -> 1458 | L68: =IF(K68<0,"STOCK ISSUE","OK") -> OK | M68: =K68*E68 -> 1866312.9 | N68: =Table5[[#This Row],[Total Qty Sold]]*Table5[[#This Row],[Unit Price]] -> 23601.24 | O68: =IFERROR(_xlfn.MAXIFS(Table3[Date],Table3[Item ID],Table5[[#This Row],[Item ID]]),"") -> 45862 | P68: =IF(Table5[[#This Row],[Last sale Date]]="","Never Sold",TODAY()-Table5[[#This Row],[Last sale Date]]) -> 190 | Q68: =IF(Table5[[#This Row],[Re order Level]]<=Table5[[#This Row],[Current stock]],"ORDERASAP","OK BUT BE CHECKING") -> OK BUT BE CHECKING | R68: =IF(AND(ISNUMBER(B68), B68 > 60), "DEAD", "ACTIVE") -> ACTIVE | S68: =IF(Table5[[#This Row],[DEADSTOCK FLAG]]="DEAD",Table5[[#This Row],[Inventory Value]],0) -> 0
A69: ='Inventory master'!A69 -> ITEM068-A | B69: ='Inventory master'!B69 -> 1x16 PLC Splitter | C69: ='Inventory master'!C69 -> Splitters | D69: ='Inventory master'!D69 -> AFL | E69: ='Inventory master'!E69 -> 377.47 | F69: ='Inventory master'!F69 -> 550.11 | G69: ='Inventory master'!G69 -> 90 | H69: =IFERROR(_xlfn.XLOOKUP(A69, 'Opening stock'!A69:A668, 'Opening stock'!E69:E668), "") -> 1350 | I69: =IFERROR(SUMIF(Table3[Item ID],'Inventory calculations'!A69,Table3[Quantity]),0) -> 0 | J69: =IFERROR(SUMIF(Table4[Item ID],'Inventory calculations'!A69,Table4[Quantity Purchased]),0) -> 0 | K69: =H69+J69-I69 -> 1350 | L69: =IF(K69<0,"STOCK ISSUE","OK") -> OK | M69: =K69*E69 -> 509584.5 | N69: =Table5[[#This Row],[Total Qty Sold]]*Table5[[#This Row],[Unit Price]] -> 0 | P69: =IF(Table5[[#This Row],[Last sale Date]]="","Never Sold",TODAY()-Table5[[#This Row],[Last sale Date]]) -> Never Sold | Q69: =IF(Table5[[#This Row],[Re order Level]]<=Table5[[#This Row],[Current stock]],"ORDERASAP","OK BUT BE CHECKING") -> OK BUT BE CHECKING | R69: =IF(AND(ISNUMBER(B69), B69 > 60), "DEAD", "ACTIVE") -> ACTIVE | S69: =IF(Table5[[#This Row],[DEADSTOCK FLAG]]="DEAD",Table5[[#This Row],[Inventory Value]],0) -> 0
A70: ='Inventory master'!A70 -> ITEM069-A | B70: ='Inventory master'!B70 -> 1x4 PLC Splitter | C70: ='Inventory master'!C70 -> Splitters | D70: ='Inventory master'!D70 -> Corning Inc. | E70: ='Inventory master'!E70 -> 1914.82 | F70: ='Inventory master'!F70 -> 3155.84 | G70: ='Inventory master'!G70 -> 57 | H70: =IFERROR(_xlfn.XLOOKUP(A70, 'Opening stock'!A70:A669, 'Opening stock'!E70:E669), "") -> 855 | I70: =IFERROR(SUMIF(Table3[Item ID],'Inventory calculations'!A70,Table3[Quantity]),0) -> 0 | J70: =IFERROR(SUMIF(Table4[Item ID],'Inventory calculations'!A70,Table4[Quantity Purchased]),0) -> 0 | K70: =H70+J70-I70 -> 855 | L70: =IF(K70<0,"STOCK ISSUE","OK") -> OK | M70: =K70*E70 -> 1637171.1 | N70: =Table5[[#This Row],[Total Qty Sold]]*Table5[[#This Row],[Unit Price]] -> 0 | P70: =IF(Table5[[#This Row],[Last sale Date]]="","Never Sold",TODAY()-Table5[[#This Row],[Last sale Date]]) -> Never Sold | Q70: =IF(Table5[[#This Row],[Re order Level]]<=Table5[[#This Row],[Current stock]],"ORDERASAP","OK BUT BE CHECKING") -> OK BUT BE CHECKING | R70: =IF(AND(ISNUMBER(B70), B70 > 60), "DEAD", "ACTIVE") -> ACTIVE | S70: =IF(Table5[[#This Row],[DEADSTOCK FLAG]]="DEAD",Table5[[#This Row],[Inventory Value]],0) -> 0
A71: ='Inventory master'!A71 -> ITEM070-A | B71: ='Inventory master'!B71 -> Fusion Splicer | C71: ='Inventory master'!C71 -> Splicers | D71: ='Inventory master'!D71 -> TE Connectivity | E71: ='Inventory master'!E71 -> 76.51 | F71: ='Inventory master'!F71 -> 132.36 | G71: ='Inventory master'!G71 -> 52 | H71: =IFERROR(_xlfn.XLOOKUP(A71, 'Opening stock'!A71:A670, 'Opening stock'!E71:E670), "") -> 780 | I71: =IFERROR(SUMIF(Table3[Item ID],'Inventory calculations'!A71,Table3[Quantity]),0) -> 0 | J71: =IFERROR(SUMIF(Table4[Item ID],'Inventory calculations'!A71,Table4[Quantity Purchased]),0) -> 8 | K71: =H71+J71-I71 -> 788 | L71: =IF(K71<0,"STOCK ISSUE","OK") -> OK | M71: =K71*E71 -> 60289.88 | N71: =Table5[[#This Row],[Total Qty Sold]]*Table5[[#This Row],[Unit Price]] -> 0 | P71: =IF(Table5[[#This Row],[Last sale Date]]="","Never Sold",TODAY()-Table5[[#This Row],[Last sale Date]]) -> Never Sold | Q71: =IF(Table5[[#This Row],[Re order Level]]<=Table5[[#This Row],[Current stock]],"ORDERASAP","OK BUT BE CHECKING") -> OK BUT BE CHECKING | R71: =IF(AND(ISNUMBER(B71), B71 > 60), "DEAD", "ACTIVE") -> ACTIVE | S71: =IF(Table5[[#This Row],[DEADSTOCK FLAG]]="DEAD",Table5[[#This Row],[Inventory Value]],0) -> 0
A72: ='Inventory master'!A72 -> ITEM071-A | B72: ='Inventory master'!B72 -> Fiber Cleaner | C72: ='Inventory master'!C72 -> Accessories | D72: ='Inventory master'!D72 -> HellermannTyton | E72: ='Inventory master'!E72 -> 1404.1 | F72: ='Inventory master'!F72 -> 1975.06 | G72: ='Inventory master'!G72 -> 51 | H72: =IFERROR(_xlfn.XLOOKUP(A72, 'Opening stock'!A72:A671, 'Opening stock'!E72:E671), "") -> 765 | I72: =IFERROR(SUMIF(Table3[Item ID],'Inventory calculations'!A72,Table3[Quantity]),0) -> 0 | J72: =IFERROR(SUMIF(Table4[Item ID],'Inventory calculations'!A72,Table4[Quantity Purchased]),0) -> 27 | K72: =H72+J72-I72 -> 792 | L72: =IF(K72<0,"STOCK ISSUE","OK") -> OK | M72: =K72*E72 -> 1112047.2 | N72: =Table5[[#This Row],[Total Qty Sold]]*Table5[[#This Row],[Unit Price]] -> 0 | P72: =IF(Table5[[#This Row],[Last sale Date]]="","Never Sold",TODAY()-Table5[[#This Row],[Last sale Date]]) -> Never Sold | Q72: =IF(Table5[[#This Row],[Re order Level]]<=Table5[[#This Row],[Current stock]],"ORDERASAP","OK BUT BE CHECKING") -> OK BUT BE CHECKING | R72: =IF(AND(ISNUMBER(B72), B72 > 60), "DEAD", "ACTIVE") -> ACTIVE | S72: =IF(Table5[[#This Row],[DEADSTOCK FLAG]]="DEAD",Table5[[#This Row],[Inventory Value]],0) -> 0
A73: ='Inventory master'!A73 -> ITEM072-A | B73: ='Inventory master'!B73 -> Fiber Cleaner | C73: ='Inventory master'!C73 -> Accessories | D73: ='Inventory master'!D73 -> Corning Inc. | E73: ='Inventory master'!E73 -> 1081.9 | F73: ='Inventory master'!F73 -> 1550.63 | G73: ='Inventory master'!G73 -> 65 | H73: =IFERROR(_xlfn.XLOOKUP(A73, 'Opening stock'!A73:A672, 'Opening stock'!E73:E672), "") -> 975 | I73: =IFERROR(SUMIF(Table3[Item ID],'Inventory calculations'!A73,Table3[Quantity]),0) -> 0 | J73: =IFERROR(SUMIF(Table4[Item ID],'Inventory calculations'!A73,Table4[Quantity Purchased]),0) -> 24 | K73: =H73+J73-I73 -> 999 | L73: =IF(K73<0,"STOCK ISSUE","OK") -> OK | M73: =K73*E73 -> 1080818.1 | N73: =Table5[[#This Row],[Total Qty Sold]]*Table5[[#This Row],[Unit Price]] -> 0 | P73: =IF(Table5[[#This Row],[Last sale Date]]="","Never Sold",TODAY()-Table5[[#This Row],[Last sale Date]]) -> Never Sold | Q73: =IF(Table5[[#This Row],[Re order Level]]<=Table5[[#This Row],[Current stock]],"ORDERASAP","OK BUT BE CHECKING") -> OK BUT BE CHECKING | R73: =IF(AND(ISNUMBER(B73), B73 > 60), "DEAD", "ACTIVE") -> ACTIVE | S73: =IF(Table5[[#This Row],[DEADSTOCK FLAG]]="DEAD",Table5[[#This Row],[Inventory Value]],0) -> 0
A74: ='Inventory master'!A74 -> ITEM073-A | B74: ='Inventory master'!B74 -> Fixed Attenuator 2dB | C74: ='Inventory master'!C74 -> Attenuators | D74: ='Inventory master'!D74 -> Siemon | E74: ='Inventory master'!E74 -> 1835.6 | F74: ='Inventory master'!F74 -> 2686.88 | G74: ='Inventory master'!G74 -> 47 | H74: =IFERROR(_xlfn.XLOOKUP(A74, 'Opening stock'!A74:A673, 'Opening stock'!E74:E673), "") -> 705 | I74: =IFERROR(SUMIF(Table3[Item ID],'Inventory calculations'!A74,Table3[Quantity]),0) -> 14 | J74: =IFERROR(SUMIF(Table4[Item ID],'Inventory calculations'!A74,Table4[Quantity Purchased]),0) -> 8 | K74: =H74+J74-I74 -> 699 | L74: =IF(K74<0,"STOCK ISSUE","OK") -> OK | M74: =K74*E74 -> 1283084.4 | N74: =Table5[[#This Row],[Total Qty Sold]]*Table5[[#This Row],[Unit Price]] -> 37616.32 | O74: =IFERROR(_xlfn.MAXIFS(Table3[Date],Table3[Item ID],Table5[[#This Row],[Item ID]]),"") -> 45409 | P74: =IF(Table5[[#This Row],[Last sale Date]]="","Never Sold",TODAY()-Table5[[#This Row],[Last sale Date]]) -> 643 | Q74: =IF(Table5[[#This Row],[Re order Level]]<=Table5[[#This Row],[Current stock]],"ORDERASAP","OK BUT BE CHECKING") -> OK BUT BE CHECKING | R74: =IF(AND(ISNUMBER(B74), B74 > 60), "DEAD", "ACTIVE") -> ACTIVE | S74: =IF(Table5[[#This Row],[DEADSTOCK FLAG]]="DEAD",Table5[[#This Row],[Inventory Value]],0) -> 0
A75: ='Inventory master'!A75 -> ITEM074-A | B75: ='Inventory master'!B75 -> 1x4 PLC Splitter | C75: ='Inventory master'!C75 -> Splitters | D75: ='Inventory master'!D75 -> Huber+Suhner | E75: ='Inventory master'!E75 -> 1794.85 | F75: ='Inventory master'!F75 -> 2913.22 | G75: ='Inventory master'!G75 -> 53 | H75: =IFERROR(_xlfn.XLOOKUP(A75, 'Opening stock'!A75:A674, 'Opening stock'!E75:E674), "") -> 795 | I75: =IFERROR(SUMIF(Table3[Item ID],'Inventory calculations'!A75,Table3[Quantity]),0) -> 1 | J75: =IFERROR(SUMIF(Table4[Item ID],'Inventory calculations'!A75,Table4[Quantity Purchased]),0) -> 7 | K75: =H75+J75-I75 -> 801 | L75: =IF(K75<0,"STOCK ISSUE","OK") -> OK | M75: =K75*E75 -> 1437674.8 | N75: =Table5[[#This Row],[Total Qty Sold]]*Table5[[#This Row],[Unit Price]] -> 2913.22 | O75: =IFERROR(_xlfn.MAXIFS(Table3[Date],Table3[Item ID],Table5[[#This Row],[Item ID]]),"") -> 45338 | P75: =IF(Table5[[#This Row],[Last sale Date]]="","Never Sold",TODAY()-Table5[[#This Row],[Last sale Date]]) -> 714 | Q75: =IF(Table5[[#This Row],[Re order Level]]<=Table5[[#This Row],[Current stock]],"ORDERASAP","OK BUT BE CHECKING") -> OK BUT BE CHECKING | R75: =IF(AND(ISNUMBER(B75), B75 > 60), "DEAD", "ACTIVE") -> ACTIVE | S75: =IF(Table5[[#This Row],[DEADSTOCK FLAG]]="DEAD",Table5[[#This Row],[Inventory Value]],0) -> 0
A76: ='Inventory master'!A76 -> ITEM075-A | B76: ='Inventory master'!B76 -> Mechanical Splicer | C76: ='Inventory master'!C76 -> Splicers | D76: ='Inventory master'!D76 -> Belden | E76: ='Inventory master'!E76 -> 1612.69 | F76: ='Inventory master'!F76 -> 3050.31 | G76: ='Inventory master'!G76 -> 72 | H76: =IFERROR(_xlfn.XLOOKUP(A76, 'Opening stock'!A76:A675, 'Opening stock'!E76:E675), "") -> 1080 | I76: =IFERROR(SUMIF(Table3[Item ID],'Inventory calculations'!A76,Table3[Quantity]),0) -> 0 | J76: =IFERROR(SUMIF(Table4[Item ID],'Inventory calculations'!A76,Table4[Quantity Purchased]),0) -> 6 | K76: =H76+J76-I76 -> 1086 | L76: =IF(K76<0,"STOCK ISSUE","OK") -> OK | M76: =K76*E76 -> 1751381.3 | N76: =Table5[[#This Row],[Total Qty Sold]]*Table5[[#This Row],[Unit Price]] -> 0 | P76: =IF(Table5[[#This Row],[Last sale Date]]="","Never Sold",TODAY()-Table5[[#This Row],[Last sale Date]]) -> Never Sold | Q76: =IF(Table5[[#This Row],[Re order Level]]<=Table5[[#This Row],[Current stock]],"ORDERASAP","OK BUT BE CHECKING") -> OK BUT BE CHECKING | R76: =IF(AND(ISNUMBER(B76), B76 > 60), "DEAD", "ACTIVE") -> ACTIVE | S76: =IF(Table5[[#This Row],[DEADSTOCK FLAG]]="DEAD",Table5[[#This Row],[Inventory Value]],0) -> 0
A77: ='Inventory master'!A77 -> ITEM076-A | B77: ='Inventory master'!B77 -> Fusion Splicer | C77: ='Inventory master'!C77 -> Splicers | D77: ='Inventory master'!D77 -> Prysmian Group | E77: ='Inventory master'!E77 -> 736.95 | F77: ='Inventory master'!F77 -> 1382.2 | G77: ='Inventory master'!G77 -> 25 | H77: =IFERROR(_xlfn.XLOOKUP(A77, 'Opening stock'!A77:A676, 'Opening stock'!E77:E676), "") -> 375 | I77: =IFERROR(SUMIF(Table3[Item ID],'Inventory calculations'!A77,Table3[Quantity]),0) -> 0 | J77: =IFERROR(SUMIF(Table4[Item ID],'Inventory calculations'!A77,Table4[Quantity Purchased]),0) -> 15 | K77: =H77+J77-I77 -> 390 | L77: =IF(K77<0,"STOCK ISSUE","OK") -> OK | M77: =K77*E77 -> 287410.5 | N77: =Table5[[#This Row],[Total Qty Sold]]*Table5[[#This Row],[Unit Price]] -> 0 | P77: =IF(Table5[[#This Row],[Last sale Date]]="","Never Sold",TODAY()-Table5[[#This Row],[Last sale Date]]) -> Never Sold | Q77: =IF(Table5[[#This Row],[Re order Level]]<=Table5[[#This Row],[Current stock]],"ORDERASAP","OK BUT BE CHECKING") -> OK BUT BE CHECKING | R77: =IF(AND(ISNUMBER(B77), B77 > 60), "DEAD", "ACTIVE") -> ACTIVE | S77: =IF(Table5[[#This Row],[DEADSTOCK FLAG]]="DEAD",Table5[[#This Row],[Inventory Value]],0) -> 0
A78: ='Inventory master'!A78 -> ITEM077-A | B78: ='Inventory master'!B78 -> Fiber Optic Cutter | C78: ='Inventory master'!C78 -> Tools | D78: ='Inventory master'!D78 -> AFL | E78: ='Inventory master'!E78 -> 945.5 | F78: ='Inventory master'!F78 -> 1063.23 | G78: ='Inventory master'!G78 -> 47 | H78: =IFERROR(_xlfn.XLOOKUP(A78, 'Opening stock'!A78:A677, 'Opening stock'!E78:E677), "") -> 705 | I78: =IFERROR(SUMIF(Table3[Item ID],'Inventory calculations'!A78,Table3[Quantity]),0) -> 10 | J78: =IFERROR(SUMIF(Table4[Item ID],'Inventory calculations'!A78,Table4[Quantity Purchased]),0) -> 2 | K78: =H78+J78-I78 -> 697 | L78: =IF(K78<0,"STOCK ISSUE","OK") -> OK | M78: =K78*E78 -> 659013.5 | N78: =Table5[[#This Row],[Total Qty Sold]]*Table5[[#This Row],[Unit Price]] -> 10632.3 | O78: =IFERROR(_xlfn.MAXIFS(Table3[Date],Table3[Item ID],Table5[[#This Row],[Item ID]]),"") -> 45601 | P78: =IF(Table5[[#This Row],[Last sale Date]]="","Never Sold",TODAY()-Table5[[#This Row],[Last sale Date]]) -> 451 | Q78: =IF(Table5[[#This Row],[Re order Level]]<=Table5[[#This Row],[Current stock]],"ORDERASAP","OK BUT BE CHECKING") -> OK BUT BE CHECKING | R78: =IF(AND(ISNUMBER(B78), B78 > 60), "DEAD", "ACTIVE") -> ACTIVE | S78: =IF(Table5[[#This Row],[DEADSTOCK FLAG]]="DEAD",Table5[[#This Row],[Inventory Value]],0) -> 0
A79: ='Inventory master'!A79 -> ITEM078-A | B79: ='Inventory master'!B79 -> 1x32 PLC Splitter | C79: ='Inventory master'!C79 -> Splitters | D79: ='Inventory master'!D79 -> TE Connectivity | E79: ='Inventory master'!E79 -> 1445.39 | F79: ='Inventory master'!F79 -> 2054.96 | G79: ='Inventory master'!G79 -> 100 | H79: =IFERROR(_xlfn.XLOOKUP(A79, 'Opening stock'!A79:A678, 'Opening stock'!E79:E678), "") -> 1500 | I79: =IFERROR(SUMIF(Table3[Item ID],'Inventory calculations'!A79,Table3[Quantity]),0) -> 0 | J79: =IFERROR(SUMIF(Table4[Item ID],'Inventory calculations'!A79,Table4[Quantity Purchased]),0) -> 27 | K79: =H79+J79-I79 -> 1527 | L79: =IF(K79<0,"STOCK ISSUE","OK") -> OK | M79: =K79*E79 -> 2207110.5 | N79: =Table5[[#This Row],[Total Qty Sold]]*Table5[[#This Row],[Unit Price]] -> 0 | P79: =IF(Table5[[#This Row],[Last sale Date]]="","Never Sold",TODAY()-Table5[[#This Row],[Last sale Date]]) -> Never Sold | Q79: =IF(Table5[[#This Row],[Re order Level]]<=Table5[[#This Row],[Current stock]],"ORDERASAP","OK BUT BE CHECKING") -> OK BUT BE CHECKING | R79: =IF(AND(ISNUMBER(B79), B79 > 60), "DEAD", "ACTIVE") -> ACTIVE | S79: =IF(Table5[[#This Row],[DEADSTOCK FLAG]]="DEAD",Table5[[#This Row],[Inventory Value]],0) -> 0
A80: ='Inventory master'!A80 -> ITEM079-A | B80: ='Inventory master'!B80 -> QSFP Transceiver | C80: ='Inventory master'!C80 -> Transceivers | D80: ='Inventory master'!D80 -> HellermannTyton | E80: ='Inventory master'!E80 -> 844.54 | F80: ='Inventory master'!F80 -> 1448.27 | G80: ='Inventory master'!G80 -> 93 | H80: =IFERROR(_xlfn.XLOOKUP(A80, 'Opening stock'!A80:A679, 'Opening stock'!E80:E679), "") -> 1395 | I80: =IFERROR(SUMIF(Table3[Item ID],'Inventory calculations'!A80,Table3[Quantity]),0) -> 0 | J80: =IFERROR(SUMIF(Table4[Item ID],'Inventory calculations'!A80,Table4[Quantity Purchased]),0) -> 0 | K80: =H80+J80-I80 -> 1395 | L80: =IF(K80<0,"STOCK ISSUE","OK") -> OK | M80: =K80*E80 -> 1178133.3 | N80: =Table5[[#This Row],[Total Qty Sold]]*Table5[[#This Row],[Unit Price]] -> 0 | P80: =IF(Table5[[#This Row],[Last sale Date]]="","Never Sold",TODAY()-Table5[[#This Row],[Last sale Date]]) -> Never Sold | Q80: =IF(Table5[[#This Row],[Re order Level]]<=Table5[[#This Row],[Current stock]],"ORDERASAP","OK BUT BE CHECKING") -> OK BUT BE CHECKING | R80: =IF(AND(ISNUMBER(B80), B80 > 60), "DEAD", "ACTIVE") -> ACTIVE | S80: =IF(Table5[[#This Row],[DEADSTOCK FLAG]]="DEAD",Table5[[#This Row],[Inventory Value]],0) -> 0
A81: ='Inventory master'!A81 -> ITEM080-A | B81: ='Inventory master'!B81 -> ST UPC Connector | C81: ='Inventory master'!C81 -> Connectors | D81: ='Inventory master'!D81 -> Prysmian Group | E81: ='Inventory master'!E81 -> 1560.52 | F81: ='Inventory master'!F81 -> 2251.27 | G81: ='Inventory master'!G81 -> 52 | H81: =IFERROR(_xlfn.XLOOKUP(A81, 'Opening stock'!A81:A680, 'Opening stock'!E81:E680), "") -> 780 | I81: =IFERROR(SUMIF(Table3[Item ID],'Inventory calculations'!A81,Table3[Quantity]),0) -> 0 | J81: =IFERROR(SUMIF(Table4[Item ID],'Inventory calculations'!A81,Table4[Quantity Purchased]),0) -> 13 | K81: =H81+J81-I81 -> 793 | L81: =IF(K81<0,"STOCK ISSUE","OK") -> OK | M81: =K81*E81 -> 1237492.4 | N81: =Table5[[#This Row],[Total Qty Sold]]*Table5[[#This Row],[Unit Price]] -> 0 | P81: =IF(Table5[[#This Row],[Last sale Date]]="","Never Sold",TODAY()-Table5[[#This Row],[Last sale Date]]) -> Never Sold | Q81: =IF(Table5[[#This Row],[Re order Level]]<=Table5[[#This Row],[Current stock]],"ORDERASAP","OK BUT BE CHECKING") -> OK BUT BE CHECKING | R81: =IF(AND(ISNUMBER(B81), B81 > 60), "DEAD", "ACTIVE") -> ACTIVE | S81: =IF(Table5[[#This Row],[DEADSTOCK FLAG]]="DEAD",Table5[[#This Row],[Inventory Value]],0) -> 0
A82: ='Inventory master'!A82 -> ITEM081-A | B82: ='Inventory master'!B82 -> Fiber Optic Stripper | C82: ='Inventory master'!C82 -> Tools | D82: ='Inventory master'!D82 -> CommScope | E82: ='Inventory master'!E82 -> 1824.39 | F82: ='Inventory master'!F82 -> 3319.66 | G82: ='Inventory master'!G82 -> 26 | H82: =IFERROR(_xlfn.XLOOKUP(A82, 'Opening stock'!A82:A681, 'Opening stock'!E82:E681), "") -> 390 | I82: =IFERROR(SUMIF(Table3[Item ID],'Inventory calculations'!A82,Table3[Quantity]),0) -> 0 | J82: =IFERROR(SUMIF(Table4[Item ID],'Inventory calculations'!A82,Table4[Quantity Purchased]),0) -> 7 | K82: =H82+J82-I82 -> 397 | L82: =IF(K82<0,"STOCK ISSUE","OK") -> OK | M82: =K82*E82 -> 724282.83 | N82: =Table5[[#This Row],[Total Qty Sold]]*Table5[[#This Row],[Unit Price]] -> 0 | P82: =IF(Table5[[#This Row],[Last sale Date]]="","Never Sold",TODAY()-Table5[[#This Row],[Last sale Date]]) -> Never Sold | Q82: =IF(Table5[[#This Row],[Re order Level]]<=Table5[[#This Row],[Current stock]],"ORDERASAP","OK BUT BE CHECKING") -> OK BUT BE CHECKING | R82: =IF(AND(ISNUMBER(B82), B82 > 60), "DEAD", "ACTIVE") -> ACTIVE | S82: =IF(Table5[[#This Row],[DEADSTOCK FLAG]]="DEAD",Table5[[#This Row],[Inventory Value]],0) -> 0
A83: ='Inventory master'!A83 -> ITEM082-A | B83: ='Inventory master'!B83 -> QSFP Transceiver | C83: ='Inventory master'!C83 -> Transceivers | D83: ='Inventory master'!D83 -> Huber+Suhner | E83: ='Inventory master'!E83 -> 1055.99 | F83: ='Inventory master'!F83 -> 1292.95 | G83: ='Inventory master'!G83 -> 20 | H83: =IFERROR(_xlfn.XLOOKUP(A83, 'Opening stock'!A83:A682, 'Opening stock'!E83:E682), "") -> 300 | I83: =IFERROR(SUMIF(Table3[Item ID],'Inventory calculations'!A83,Table3[Quantity]),0) -> 3 | J83: =IFERROR(SUMIF(Table4[Item ID],'Inventory calculations'!A83,Table4[Quantity Purchased]),0) -> 0 | K83: =H83+J83-I83 -> 297 | L83: =IF(K83<0,"STOCK ISSUE","OK") -> OK | M83: =K83*E83 -> 313629.03 | N83: =Table5[[#This Row],[Total Qty Sold]]*Table5[[#This Row],[Unit Price]] -> 3878.85 | O83: =IFERROR(_xlfn.MAXIFS(Table3[Date],Table3[Item ID],Table5[[#This Row],[Item ID]]),"") -> 45473 | P83: =IF(Table5[[#This Row],[Last sale Date]]="","Never Sold",TODAY()-Table5[[#This Row],[Last sale Date]]) -> 579 | Q83: =IF(Table5[[#This Row],[Re order Level]]<=Table5[[#This Row],[Current stock]],"ORDERASAP","OK BUT BE CHECKING") -> OK BUT BE CHECKING | R83: =IF(AND(ISNUMBER(B83), B83 > 60), "DEAD", "ACTIVE") -> ACTIVE | S83: =IF(Table5[[#This Row],[DEADSTOCK FLAG]]="DEAD",Table5[[#This Row],[Inventory Value]],0) -> 0
A84: ='Inventory master'!A84 -> ITEM083-A | B84: ='Inventory master'!B84 -> Fiber Optic Tester | C84: ='Inventory master'!C84 -> Tools | D84: ='Inventory master'!D84 -> Corning Inc. | E84: ='Inventory master'!E84 -> 1947.3 | F84: ='Inventory master'!F84 -> 2469.32 | G84: ='Inventory master'!G84 -> 74 | H84: =IFERROR(_xlfn.XLOOKUP(A84, 'Opening stock'!A84:A683, 'Opening stock'!E84:E683), "") -> 1110 | I84: =IFERROR(SUMIF(Table3[Item ID],'Inventory calculations'!A84,Table3[Quantity]),0) -> 0 | J84: =IFERROR(SUMIF(Table4[Item ID],'Inventory calculations'!A84,Table4[Quantity Purchased]),0) -> 20 | K84: =H84+J84-I84 -> 1130 | L84: =IF(K84<0,"STOCK ISSUE","OK") -> OK | M84: =K84*E84 -> 2200449 | N84: =Table5[[#This Row],[Total Qty Sold]]*Table5[[#This Row],[Unit Price]] -> 0 | P84: =IF(Table5[[#This Row],[Last sale Date]]="","Never Sold",TODAY()-Table5[[#This Row],[Last sale Date]]) -> Never Sold | Q84: =IF(Table5[[#This Row],[Re order Level]]<=Table5[[#This Row],[Current stock]],"ORDERASAP","OK BUT BE CHECKING") -> OK BUT BE CHECKING | R84: =IF(AND(ISNUMBER(B84), B84 > 60), "DEAD", "ACTIVE") -> ACTIVE | S84: =IF(Table5[[#This Row],[DEADSTOCK FLAG]]="DEAD",Table5[[#This Row],[Inventory Value]],0) -> 0
A85: ='Inventory master'!A85 -> ITEM084-A | B85: ='Inventory master'!B85 -> Fiber Pigtail | C85: ='Inventory master'!C85 -> Accessories | D85: ='Inventory master'!D85 -> CommScope | E85: ='Inventory master'!E85 -> 458.62 | F85: ='Inventory master'!F85 -> 622.3 | G85: ='Inventory master'!G85 -> 59 | H85: =IFERROR(_xlfn.XLOOKUP(A85, 'Opening stock'!A85:A684, 'Opening stock'!E85:E684), "") -> 885 | I85: =IFERROR(SUMIF(Table3[Item ID],'Inventory calculations'!A85,Table3[Quantity]),0) -> 0 | J85: =IFERROR(SUMIF(Table4[Item ID],'Inventory calculations'!A85,Table4[Quantity Purchased]),0) -> 11 | K85: =H85+J85-I85 -> 896 | L85: =IF(K85<0,"STOCK ISSUE","OK") -> OK | M85: =K85*E85 -> 410923.52 | N85: =Table5[[#This Row],[Total Qty Sold]]*Table5[[#This Row],[Unit Price]] -> 0 | P85: =IF(Table5[[#This Row],[Last sale Date]]="","Never Sold",TODAY()-Table5[[#This Row],[Last sale Date]]) -> Never Sold | Q85: =IF(Table5[[#This Row],[Re order Level]]<=Table5[[#This Row],[Current stock]],"ORDERASAP","OK BUT BE CHECKING") -> OK BUT BE CHECKING | R85: =IF(AND(ISNUMBER(B85), B85 > 60), "DEAD", "ACTIVE") -> ACTIVE | S85: =IF(Table5[[#This Row],[DEADSTOCK FLAG]]="DEAD",Table5[[#This Row],[Inventory Value]],0) -> 0
A86: ='Inventory master'!A86 -> ITEM085-A | B86: ='Inventory master'!B86 -> LC APC Connector | C86: ='Inventory master'!C86 -> Connectors | D86: ='Inventory master'!D86 -> AFL | E86: ='Inventory master'!E86 -> 558.85 | F86: ='Inventory master'!F86 -> 643.35 | G86: ='Inventory master'!G86 -> 23 | H86: =IFERROR(_xlfn.XLOOKUP(A86, 'Opening stock'!A86:A685, 'Opening stock'!E86:E685), "") -> 345 | I86: =IFERROR(SUMIF(Table3[Item ID],'Inventory calculations'!A86,Table3[Quantity]),0) -> 0 | J86: =IFERROR(SUMIF(Table4[Item ID],'Inventory calculations'!A86,Table4[Quantity Purchased]),0) -> 0 | K86: =H86+J86-I86 -> 345 | L86: =IF(K86<0,"STOCK ISSUE","OK") -> OK | M86: =K86*E86 -> 192803.25 | N86: =Table5[[#This Row],[Total Qty Sold]]*Table5[[#This Row],[Unit Price]] -> 0 | P86: =IF(Table5[[#This Row],[Last sale Date]]="","Never Sold",TODAY()-Table5[[#This Row],[Last sale Date]]) -> Never Sold | Q86: =IF(Table5[[#This Row],[Re order Level]]<=Table5[[#This Row],[Current stock]],"ORDERASAP","OK BUT BE CHECKING") -> OK BUT BE CHECKING | R86: =IF(AND(ISNUMBER(B86), B86 > 60), "DEAD", "ACTIVE") -> ACTIVE | S86: =IF(Table5[[#This Row],[DEADSTOCK FLAG]]="DEAD",Table5[[#This Row],[Inventory Value]],0) -> 0
A87: ='Inventory master'!A87 -> ITEM086-A | B87: ='Inventory master'!B87 -> Fiber Jumper | C87: ='Inventory master'!C87 -> Accessories | D87: ='Inventory master'!D87 -> Panduit | E87: ='Inventory master'!E87 -> 1448.2 | F87: ='Inventory master'!F87 -> 2574.06 | G87: ='Inventory master'!G87 -> 48 | H87: =IFERROR(_xlfn.XLOOKUP(A87, 'Opening stock'!A87:A686, 'Opening stock'!E87:E686), "") -> 720 | I87: =IFERROR(SUMIF(Table3[Item ID],'Inventory calculations'!A87,Table3[Quantity]),0) -> 0 | J87: =IFERROR(SUMIF(Table4[Item ID],'Inventory calculations'!A87,Table4[Quantity Purchased]),0) -> 0 | K87: =H87+J87-I87 -> 720 | L87: =IF(K87<0,"STOCK ISSUE","OK") -> OK | M87: =K87*E87 -> 1042704 | N87: =Table5[[#This Row],[Total Qty Sold]]*Table5[[#This Row],[Unit Price]] -> 0 | P87: =IF(Table5[[#This Row],[Last sale Date]]="","Never Sold",TODAY()-Table5[[#This Row],[Last sale Date]]) -> Never Sold | Q87: =IF(Table5[[#This Row],[Re order Level]]<=Table5[[#This Row],[Current stock]],"ORDERASAP","OK BUT BE CHECKING") -> OK BUT BE CHECKING | R87: =IF(AND(ISNUMBER(B87), B87 > 60), "DEAD", "ACTIVE") -> ACTIVE | S87: =IF(Table5[[#This Row],[DEADSTOCK FLAG]]="DEAD",Table5[[#This Row],[Inventory Value]],0) -> 0
A88: ='Inventory master'!A88 -> ITEM087-A | B88: ='Inventory master'!B88 -> Indoor Fiber Cable 500m | C88: ='Inventory master'!C88 -> Fiber Optic Cables | D88: ='Inventory master'!D88 -> AFL | E88: ='Inventory master'!E88 -> 14.98 | F88: ='Inventory master'!F88 -> 28.83 | G88: ='Inventory master'!G88 -> 19 | H88: =IFERROR(_xlfn.XLOOKUP(A88, 'Opening stock'!A88:A687, 'Opening stock'!E88:E687), "") -> 285 | I88: =IFERROR(SUMIF(Table3[Item ID],'Inventory calculations'!A88,Table3[Quantity]),0) -> 0 | J88: =IFERROR(SUMIF(Table4[Item ID],'Inventory calculations'!A88,Table4[Quantity Purchased]),0) -> 23 | K88: =H88+J88-I88 -> 308 | L88: =IF(K88<0,"STOCK ISSUE","OK") -> OK | M88: =K88*E88 -> 4613.84 | N88: =Table5[[#This Row],[Total Qty Sold]]*Table5[[#This Row],[Unit Price]] -> 0 | P88: =IF(Table5[[#This Row],[Last sale Date]]="","Never Sold",TODAY()-Table5[[#This Row],[Last sale Date]]) -> Never Sold | Q88: =IF(Table5[[#This Row],[Re order Level]]<=Table5[[#This Row],[Current stock]],"ORDERASAP","OK BUT BE CHECKING") -> OK BUT BE CHECKING | R88: =IF(AND(ISNUMBER(B88), B88 > 60), "DEAD", "ACTIVE") -> ACTIVE | S88: =IF(Table5[[#This Row],[DEADSTOCK FLAG]]="DEAD",Table5[[#This Row],[Inventory Value]],0) -> 0
A89: ='Inventory master'!A89 -> ITEM088-A | B89: ='Inventory master'!B89 -> 96-Port Fiber Patch Panel | C89: ='Inventory master'!C89 -> Patch Panels | D89: ='Inventory master'!D89 -> Huber+Suhner | E89: ='Inventory master'!E89 -> 719.88 | F89: ='Inventory master'!F89 -> 1139.88 | G89: ='Inventory master'!G89 -> 22 | H89: =IFERROR(_xlfn.XLOOKUP(A89, 'Opening stock'!A89:A688, 'Opening stock'!E89:E688), "") -> 330 | I89: =IFERROR(SUMIF(Table3[Item ID],'Inventory calculations'!A89,Table3[Quantity]),0) -> 0 | J89: =IFERROR(SUMIF(Table4[Item ID],'Inventory calculations'!A89,Table4[Quantity Purchased]),0) -> 0 | K89: =H89+J89-I89 -> 330 | L89: =IF(K89<0,"STOCK ISSUE","OK") -> OK | M89: =K89*E89 -> 237560.4 | N89: =Table5[[#This Row],[Total Qty Sold]]*Table5[[#This Row],[Unit Price]] -> 0 | P89: =IF(Table5[[#This Row],[Last sale Date]]="","Never Sold",TODAY()-Table5[[#This Row],[Last sale Date]]) -> Never Sold | Q89: =IF(Table5[[#This Row],[Re order Level]]<=Table5[[#This Row],[Current stock]],"ORDERASAP","OK BUT BE CHECKING") -> OK BUT BE CHECKING | R89: =IF(AND(ISNUMBER(B89), B89 > 60), "DEAD", "ACTIVE") -> ACTIVE | S89: =IF(Table5[[#This Row],[DEADSTOCK FLAG]]="DEAD",Table5[[#This Row],[Inventory Value]],0) -> 0
A90: ='Inventory master'!A90 -> ITEM089-A | B90: ='Inventory master'!B90 -> ST UPC Connector | C90: ='Inventory master'!C90 -> Connectors | D90: ='Inventory master'!D90 -> Leviton | E90: ='Inventory master'!E90 -> 171.77 | F90: ='Inventory master'!F90 -> 259.38 | G90: ='Inventory master'!G90 -> 10 | H90: =IFERROR(_xlfn.XLOOKUP(A90, 'Opening stock'!A90:A689, 'Opening stock'!E90:E689), "") -> 150 | I90: =IFERROR(SUMIF(Table3[Item ID],'Inventory calculations'!A90,Table3[Quantity]),0) -> 17 | J90: =IFERROR(SUMIF(Table4[Item ID],'Inventory calculations'!A90,Table4[Quantity Purchased]),0) -> 3 | K90: =H90+J90-I90 -> 136 | L90: =IF(K90<0,"STOCK ISSUE","OK") -> OK | M90: =K90*E90 -> 23360.72 | N90: =Table5[[#This Row],[Total Qty Sold]]*Table5[[#This Row],[Unit Price]] -> 4409.46 | O90: =IFERROR(_xlfn.MAXIFS(Table3[Date],Table3[Item ID],Table5[[#This Row],[Item ID]]),"") -> 45482 | P90: =IF(Table5[[#This Row],[Last sale Date]]="","Never Sold",TODAY()-Table5[[#This Row],[Last sale Date]]) -> 570 | Q90: =IF(Table5[[#This Row],[Re order Level]]<=Table5[[#This Row],[Current stock]],"ORDERASAP","OK BUT BE CHECKING") -> OK BUT BE CHECKING | R90: =IF(AND(ISNUMBER(B90), B90 > 60), "DEAD", "ACTIVE") -> ACTIVE | S90: =IF(Table5[[#This Row],[DEADSTOCK FLAG]]="DEAD",Table5[[#This Row],[Inventory Value]],0) -> 0
A91: ='Inventory master'!A91 -> ITEM090-A | B91: ='Inventory master'!B91 -> 1x16 PLC Splitter | C91: ='Inventory master'!C91 -> Splitters | D91: ='Inventory master'!D91 -> Panduit | E91: ='Inventory master'!E91 -> 808.45 | F91: ='Inventory master'!F91 -> 1484.18 | G91: ='Inventory master'!G91 -> 95 | H91: =IFERROR(_xlfn.XLOOKUP(A91, 'Opening stock'!A91:A690, 'Opening stock'!E91:E690), "") -> 1425 | I91: =IFERROR(SUMIF(Table3[Item ID],'Inventory calculations'!A91,Table3[Quantity]),0) -> 0 | J91: =IFERROR(SUMIF(Table4[Item ID],'Inventory calculations'!A91,Table4[Quantity Purchased]),0) -> 7 | K91: =H91+J91-I91 -> 1432 | L91: =IF(K91<0,"STOCK ISSUE","OK") -> OK | M91: =K91*E91 -> 1157700.4 | N91: =Table5[[#This Row],[Total Qty Sold]]*Table5[[#This Row],[Unit Price]] -> 0 | P91: =IF(Table5[[#This Row],[Last sale Date]]="","Never Sold",TODAY()-Table5[[#This Row],[Last sale Date]]) -> Never Sold | Q91: =IF(Table5[[#This Row],[Re order Level]]<=Table5[[#This Row],[Current stock]],"ORDERASAP","OK BUT BE CHECKING") -> OK BUT BE CHECKING | R91: =IF(AND(ISNUMBER(B91), B91 > 60), "DEAD", "ACTIVE") -> ACTIVE | S91: =IF(Table5[[#This Row],[DEADSTOCK FLAG]]="DEAD",Table5[[#This Row],[Inventory Value]],0) -> 0
A92: ='Inventory master'!A92 -> ITEM091-A | B92: ='Inventory master'!B92 -> Fiber Pigtail | C92: ='Inventory master'!C92 -> Accessories | D92: ='Inventory master'!D92 -> CommScope | E92: ='Inventory master'!E92 -> 1302.94 | F92: ='Inventory master'!F92 -> 2096.07 | G92: ='Inventory master'!G92 -> 54 | H92: =IFERROR(_xlfn.XLOOKUP(A92, 'Opening stock'!A92:A691, 'Opening stock'!E92:E691), "") -> 810 | I92: =IFERROR(SUMIF(Table3[Item ID],'Inventory calculations'!A92,Table3[Quantity]),0) -> 0 | J92: =IFERROR(SUMIF(Table4[Item ID],'Inventory calculations'!A92,Table4[Quantity Purchased]),0) -> 4 | K92: =H92+J92-I92 -> 814 | L92: =IF(K92<0,"STOCK ISSUE","OK") -> OK | M92: =K92*E92 -> 1060593.2 | N92: =Table5[[#This Row],[Total Qty Sold]]*Table5[[#This Row],[Unit Price]] -> 0 | P92: =IF(Table5[[#This Row],[Last sale Date]]="","Never Sold",TODAY()-Table5[[#This Row],[Last sale Date]]) -> Never Sold | Q92: =IF(Table5[[#This Row],[Re order Level]]<=Table5[[#This Row],[Current stock]],"ORDERASAP","OK BUT BE CHECKING") -> OK BUT BE CHECKING | R92: =IF(AND(ISNUMBER(B92), B92 > 60), "DEAD", "ACTIVE") -> ACTIVE | S92: =IF(Table5[[#This Row],[DEADSTOCK FLAG]]="DEAD",Table5[[#This Row],[Inventory Value]],0) -> 0
A93: ='Inventory master'!A93 -> ITEM092-A | B93: ='Inventory master'!B93 -> Fiber Adapter | C93: ='Inventory master'!C93 -> Accessories | D93: ='Inventory master'!D93 -> Belden | E93: ='Inventory master'!E93 -> 912.7 | F93: ='Inventory master'!F93 -> 1041.48 | G93: ='Inventory master'!G93 -> 53 | H93: =IFERROR(_xlfn.XLOOKUP(A93, 'Opening stock'!A93:A692, 'Opening stock'!E93:E692), "") -> 795 | I93: =IFERROR(SUMIF(Table3[Item ID],'Inventory calculations'!A93,Table3[Quantity]),0) -> 0 | J93: =IFERROR(SUMIF(Table4[Item ID],'Inventory calculations'!A93,Table4[Quantity Purchased]),0) -> 0 | K93: =H93+J93-I93 -> 795 | L93: =IF(K93<0,"STOCK ISSUE","OK") -> OK | M93: =K93*E93 -> 725596.5 | N93: =Table5[[#This Row],[Total Qty Sold]]*Table5[[#This Row],[Unit Price]] -> 0 | P93: =IF(Table5[[#This Row],[Last sale Date]]="","Never Sold",TODAY()-Table5[[#This Row],[Last sale Date]]) -> Never Sold | Q93: =IF(Table5[[#This Row],[Re order Level]]<=Table5[[#This Row],[Current stock]],"ORDERASAP","OK BUT BE CHECKING") -> OK BUT BE CHECKING | R93: =IF(AND(ISNUMBER(B93), B93 > 60), "DEAD", "ACTIVE") -> ACTIVE | S93: =IF(Table5[[#This Row],[DEADSTOCK FLAG]]="DEAD",Table5[[#This Row],[Inventory Value]],0) -> 0
A94: ='Inventory master'!A94 -> ITEM093-A | B94: ='Inventory master'!B94 -> Pedestal Enclosure | C94: ='Inventory master'!C94 -> Enclosures | D94: ='Inventory master'!D94 -> Huber+Suhner | E94: ='Inventory master'!E94 -> 1076.38 | F94: ='Inventory master'!F94 -> 1711.33 | G94: ='Inventory master'!G94 -> 82 | H94: =IFERROR(_xlfn.XLOOKUP(A94, 'Opening stock'!A94:A693, 'Opening stock'!E94:E693), "") -> 1230 | I94: =IFERROR(SUMIF(Table3[Item ID],'Inventory calculations'!A94,Table3[Quantity]),0) -> 3 | J94: =IFERROR(SUMIF(Table4[Item ID],'Inventory calculations'!A94,Table4[Quantity Purchased]),0) -> 4 | K94: =H94+J94-I94 -> 1231 | L94: =IF(K94<0,"STOCK ISSUE","OK") -> OK | M94: =K94*E94 -> 1325023.8 | N94: =Table5[[#This Row],[Total Qty Sold]]*Table5[[#This Row],[Unit Price]] -> 5133.99 | O94: =IFERROR(_xlfn.MAXIFS(Table3[Date],Table3[Item ID],Table5[[#This Row],[Item ID]]),"") -> 45419 | P94: =IF(Table5[[#This Row],[Last sale Date]]="","Never Sold",TODAY()-Table5[[#This Row],[Last sale Date]]) -> 633 | Q94: =IF(Table5[[#This Row],[Re order Level]]<=Table5[[#This Row],[Current stock]],"ORDERASAP","OK BUT BE CHECKING") -> OK BUT BE CHECKING | R94: =IF(AND(ISNUMBER(B94), B94 > 60), "DEAD", "ACTIVE") -> ACTIVE | S94: =IF(Table5[[#This Row],[DEADSTOCK FLAG]]="DEAD",Table5[[#This Row],[Inventory Value]],0) -> 0
A95: ='Inventory master'!A95 -> ITEM094-A | B95: ='Inventory master'!B95 -> Fiber Adapter | C95: ='Inventory master'!C95 -> Accessories | D95: ='Inventory master'!D95 -> Leviton | E95: ='Inventory master'!E95 -> 298.77 | F95: ='Inventory master'!F95 -> 572.18 | G95: ='Inventory master'!G95 -> 34 | H95: =IFERROR(_xlfn.XLOOKUP(A95, 'Opening stock'!A95:A694, 'Opening stock'!E95:E694), "") -> 510 | I95: =IFERROR(SUMIF(Table3[Item ID],'Inventory calculations'!A95,Table3[Quantity]),0) -> 0 | J95: =IFERROR(SUMIF(Table4[Item ID],'Inventory calculations'!A95,Table4[Quantity Purchased]),0) -> 25 | K95: =H95+J95-I95 -> 535 | L95: =IF(K95<0,"STOCK ISSUE","OK") -> OK | M95: =K95*E95 -> 159841.95 | N95: =Table5[[#This Row],[Total Qty Sold]]*Table5[[#This Row],[Unit Price]] -> 0 | P95: =IF(Table5[[#This Row],[Last sale Date]]="","Never Sold",TODAY()-Table5[[#This Row],[Last sale Date]]) -> Never Sold | Q95: =IF(Table5[[#This Row],[Re order Level]]<=Table5[[#This Row],[Current stock]],"ORDERASAP","OK BUT BE CHECKING") -> OK BUT BE CHECKING | R95: =IF(AND(ISNUMBER(B95), B95 > 60), "DEAD", "ACTIVE") -> ACTIVE | S95: =IF(Table5[[#This Row],[DEADSTOCK FLAG]]="DEAD",Table5[[#This Row],[Inventory Value]],0) -> 0
A96: ='Inventory master'!A96 -> ITEM095-A | B96: ='Inventory master'!B96 -> Fiber Optic Tester | C96: ='Inventory master'!C96 -> Tools | D96: ='Inventory master'!D96 -> Amphenol | E96: ='Inventory master'!E96 -> 1806.12 | F96: ='Inventory master'!F96 -> 2752.77 | G96: ='Inventory master'!G96 -> 84 | H96: =IFERROR(_xlfn.XLOOKUP(A96, 'Opening stock'!A96:A695, 'Opening stock'!E96:E695), "") -> 1260 | I96: =IFERROR(SUMIF(Table3[Item ID],'Inventory calculations'!A96,Table3[Quantity]),0) -> 12 | J96: =IFERROR(SUMIF(Table4[Item ID],'Inventory calculations'!A96,Table4[Quantity Purchased]),0) -> 0 | K96: =H96+J96-I96 -> 1248 | L96: =IF(K96<0,"STOCK ISSUE","OK") -> OK | M96: =K96*E96 -> 2254037.8 | N96: =Table5[[#This Row],[Total Qty Sold]]*Table5[[#This Row],[Unit Price]] -> 33033.24 | O96: =IFERROR(_xlfn.MAXIFS(Table3[Date],Table3[Item ID],Table5[[#This Row],[Item ID]]),"") -> 45396 | P96: =IF(Table5[[#This Row],[Last sale Date]]="","Never Sold",TODAY()-Table5[[#This Row],[Last sale Date]]) -> 656 | Q96: =IF(Table5[[#This Row],[Re order Level]]<=Table5[[#This Row],[Current stock]],"ORDERASAP","OK BUT BE CHECKING") -> OK BUT BE CHECKING | R96: =IF(AND(ISNUMBER(B96), B96 > 60), "DEAD", "ACTIVE") -> ACTIVE | S96: =IF(Table5[[#This Row],[DEADSTOCK FLAG]]="DEAD",Table5[[#This Row],[Inventory Value]],0) -> 0
A97: ='Inventory master'!A97 -> ITEM096-A | B97: ='Inventory master'!B97 -> 1x16 PLC Splitter | C97: ='Inventory master'!C97 -> Splitters | D97: ='Inventory master'!D97 -> Amphenol | E97: ='Inventory master'!E97 -> 563.28 | F97: ='Inventory master'!F97 -> 799.09 | G97: ='Inventory master'!G97 -> 84 | H97: =IFERROR(_xlfn.XLOOKUP(A97, 'Opening stock'!A97:A696, 'Opening stock'!E97:E696), "") -> 1260 | I97: =IFERROR(SUMIF(Table3[Item ID],'Inventory calculations'!A97,Table3[Quantity]),0) -> 11 | J97: =IFERROR(SUMIF(Table4[Item ID],'Inventory calculations'!A97,Table4[Quantity Purchased]),0) -> 9 | K97: =H97+J97-I97 -> 1258 | L97: =IF(K97<0,"STOCK ISSUE","OK") -> OK | M97: =K97*E97 -> 708606.24 | N97: =Table5[[#This Row],[Total Qty Sold]]*Table5[[#This Row],[Unit Price]] -> 8789.99 | O97: =IFERROR(_xlfn.MAXIFS(Table3[Date],Table3[Item ID],Table5[[#This Row],[Item ID]]),"") -> 45372 | P97: =IF(Table5[[#This Row],[Last sale Date]]="","Never Sold",TODAY()-Table5[[#This Row],[Last sale Date]]) -> 680 | Q97: =IF(Table5[[#This Row],[Re order Level]]<=Table5[[#This Row],[Current stock]],"ORDERASAP","OK BUT BE CHECKING") -> OK BUT BE CHECKING | R97: =IF(AND(ISNUMBER(B97), B97 > 60), "DEAD", "ACTIVE") -> ACTIVE | S97: =IF(Table5[[#This Row],[DEADSTOCK FLAG]]="DEAD",Table5[[#This Row],[Inventory Value]],0) -> 0
A98: ='Inventory master'!A98 -> ITEM097-A | B98: ='Inventory master'!B98 -> 1x16 PLC Splitter | C98: ='Inventory master'!C98 -> Splitters | D98: ='Inventory master'!D98 -> Leviton | E98: ='Inventory master'!E98 -> 371.14 | F98: ='Inventory master'!F98 -> 704.64 | G98: ='Inventory master'!G98 -> 65 | H98: =IFERROR(_xlfn.XLOOKUP(A98, 'Opening stock'!A98:A697, 'Opening stock'!E98:E697), "") -> 975 | I98: =IFERROR(SUMIF(Table3[Item ID],'Inventory calculations'!A98,Table3[Quantity]),0) -> 0 | J98: =IFERROR(SUMIF(Table4[Item ID],'Inventory calculations'!A98,Table4[Quantity Purchased]),0) -> 1 | K98: =H98+J98-I98 -> 976 | L98: =IF(K98<0,"STOCK ISSUE","OK") -> OK | M98: =K98*E98 -> 362232.64 | N98: =Table5[[#This Row],[Total Qty Sold]]*Table5[[#This Row],[Unit Price]] -> 0 | P98: =IF(Table5[[#This Row],[Last sale Date]]="","Never Sold",TODAY()-Table5[[#This Row],[Last sale Date]]) -> Never Sold | Q98: =IF(Table5[[#This Row],[Re order Level]]<=Table5[[#This Row],[Current stock]],"ORDERASAP","OK BUT BE CHECKING") -> OK BUT BE CHECKING | R98: =IF(AND(ISNUMBER(B98), B98 > 60), "DEAD", "ACTIVE") -> ACTIVE | S98: =IF(Table5[[#This Row],[DEADSTOCK FLAG]]="DEAD",Table5[[#This Row],[Inventory Value]],0) -> 0
A99: ='Inventory master'!A99 -> ITEM098-A | B99: ='Inventory master'!B99 -> Fiber Optic Polisher | C99: ='Inventory master'!C99 -> Tools | D99: ='Inventory master'!D99 -> Amphenol | E99: ='Inventory master'!E99 -> 689.76 | F99: ='Inventory master'!F99 -> 1067.65 | G99: ='Inventory master'!G99 -> 76 | H99: =IFERROR(_xlfn.XLOOKUP(A99, 'Opening stock'!A99:A698, 'Opening stock'!E99:E698), "") -> 1140 | I99: =IFERROR(SUMIF(Table3[Item ID],'Inventory calculations'!A99,Table3[Quantity]),0) -> 0 | J99: =IFERROR(SUMIF(Table4[Item ID],'Inventory calculations'!A99,Table4[Quantity Purchased]),0) -> 0 | K99: =H99+J99-I99 -> 1140 | L99: =IF(K99<0,"STOCK ISSUE","OK") -> OK | M99: =K99*E99 -> 786326.4 | N99: =Table5[[#This Row],[Total Qty Sold]]*Table5[[#This Row],[Unit Price]] -> 0 | P99: =IF(Table5[[#This Row],[Last sale Date]]="","Never Sold",TODAY()-Table5[[#This Row],[Last sale Date]]) -> Never Sold | Q99: =IF(Table5[[#This Row],[Re order Level]]<=Table5[[#This Row],[Current stock]],"ORDERASAP","OK BUT BE CHECKING") -> OK BUT BE CHECKING | R99: =IF(AND(ISNUMBER(B99), B99 > 60), "DEAD", "ACTIVE") -> ACTIVE | S99: =IF(Table5[[#This Row],[DEADSTOCK FLAG]]="DEAD",Table5[[#This Row],[Inventory Value]],0) -> 0
A100: ='Inventory master'!A100 -> ITEM099-A | B100: ='Inventory master'!B100 -> Fusion Splicer | C100: ='Inventory master'!C100 -> Splicers | D100: ='Inventory master'!D100 -> Siemon | E100: ='Inventory master'!E100 -> 185.96 | F100: ='Inventory master'!F100 -> 350.67 | G100: ='Inventory master'!G100 -> 55 | H100: =IFERROR(_xlfn.XLOOKUP(A100, 'Opening stock'!A100:A699, 'Opening stock'!E100:E699), "") -> 825 | I100: =IFERROR(SUMIF(Table3[Item ID],'Inventory calculations'!A100,Table3[Quantity]),0) -> 0 | J100: =IFERROR(SUMIF(Table4[Item ID],'Inventory calculations'!A100,Table4[Quantity Purchased]),0) -> 0 | K100: =H100+J100-I100 -> 825 | L100: =IF(K100<0,"STOCK ISSUE","OK") -> OK | M100: =K100*E100 -> 153417 | N100: =Table5[[#This Row],[Total Qty Sold]]*Table5[[#This Row],[Unit Price]] -> 0 | P100: =IF(Table5[[#This Row],[Last sale Date]]="","Never Sold",TODAY()-Table5[[#This Row],[Last sale Date]]) -> Never Sold | Q100: =IF(Table5[[#This Row],[Re order Level]]<=Table5[[#This Row],[Current stock]],"ORDERASAP","OK BUT BE CHECKING") -> OK BUT BE CHECKING | R100: =IF(AND(ISNUMBER(B100), B100 > 60), "DEAD", "ACTIVE") -> ACTIVE | S100: =IF(Table5[[#This Row],[DEADSTOCK FLAG]]="DEAD",Table5[[#This Row],[Inventory Value]],0) -> 0
A101: ='Inventory master'!A101 -> ITEM100-A | B101: ='Inventory master'!B101 -> 1x8 PLC Splitter | C101: ='Inventory master'!C101 -> Splitters | D101: ='Inventory master'!D101 -> AFL | E101: ='Inventory master'!E101 -> 691.44 | F101: ='Inventory master'!F101 -> 1277.38 | G101: ='Inventory master'!G101 -> 20 | H101: =IFERROR(_xlfn.XLOOKUP(A101, 'Opening stock'!A101:A700, 'Opening stock'!E101:E700), "") -> 300 | I101: =IFERROR(SUMIF(Table3[Item ID],'Inventory calculations'!A101,Table3[Quantity]),0) -> 0 | J101: =IFERROR(SUMIF(Table4[Item ID],'Inventory calculations'!A101,Table4[Quantity Purchased]),0) -> 6 | K101: =H101+J101-I101 -> 306 | L101: =IF(K101<0,"STOCK ISSUE","OK") -> OK | M101: =K101*E101 -> 211580.64 | N101: =Table5[[#This Row],[Total Qty Sold]]*Table5[[#This Row],[Unit Price]] -> 0 | P101: =IF(Table5[[#This Row],[Last sale Date]]="","Never Sold",TODAY()-Table5[[#This Row],[Last sale Date]]) -> Never Sold | Q101: =IF(Table5[[#This Row],[Re order Level]]<=Table5[[#This Row],[Current stock]],"ORDERASAP","OK BUT BE CHECKING") -> OK BUT BE CHECKING | R101: =IF(AND(ISNUMBER(B101), B101 > 60), "DEAD", "ACTIVE") -> ACTIVE | S101: =IF(Table5[[#This Row],[DEADSTOCK FLAG]]="DEAD",Table5[[#This Row],[Inventory Value]],0) -> 0
A102: ='Inventory master'!A102 -> ITEM101-A | B102: ='Inventory master'!B102 -> 1x2 PLC Splitter | C102: ='Inventory master'!C102 -> Splitters | D102: ='Inventory master'!D102 -> Corning Inc. | E102: ='Inventory master'!E102 -> 1496.56 | F102: ='Inventory master'!F102 -> 1991.0 | G102: ='Inventory master'!G102 -> 28 | H102: =IFERROR(_xlfn.XLOOKUP(A102, 'Opening stock'!A102:A701, 'Opening stock'!E102:E701), "") -> 420 | I102: =IFERROR(SUMIF(Table3[Item ID],'Inventory calculations'!A102,Table3[Quantity]),0) -> 0 | J102: =IFERROR(SUMIF(Table4[Item ID],'Inventory calculations'!A102,Table4[Quantity Purchased]),0) -> 2 | K102: =H102+J102-I102 -> 422 | L102: =IF(K102<0,"STOCK ISSUE","OK") -> OK | M102: =K102*E102 -> 631548.32 | N102: =Table5[[#This Row],[Total Qty Sold]]*Table5[[#This Row],[Unit Price]] -> 0 | P102: =IF(Table5[[#This Row],[Last sale Date]]="","Never Sold",TODAY()-Table5[[#This Row],[Last sale Date]]) -> Never Sold | Q102: =IF(Table5[[#This Row],[Re order Level]]<=Table5[[#This Row],[Current stock]],"ORDERASAP","OK BUT BE CHECKING") -> OK BUT BE CHECKING | R102: =IF(AND(ISNUMBER(B102), B102 > 60), "DEAD", "ACTIVE") -> ACTIVE | S102: =IF(Table5[[#This Row],[DEADSTOCK FLAG]]="DEAD",Table5[[#This Row],[Inventory Value]],0) -> 0
A103: ='Inventory master'!A103 -> ITEM102-A | B103: ='Inventory master'!B103 -> FC UPC Connector | C103: ='Inventory master'!C103 -> Connectors | D103: ='Inventory master'!D103 -> AFL | E103: ='Inventory master'!E103 -> 1130.17 | F103: ='Inventory master'!F103 -> 1707.35 | G103: ='Inventory master'!G103 -> 51 | H103: =IFERROR(_xlfn.XLOOKUP(A103, 'Opening stock'!A103:A702, 'Opening stock'!E103:E702), "") -> 765 | I103: =IFERROR(SUMIF(Table3[Item ID],'Inventory calculations'!A103,Table3[Quantity]),0) -> 5 | J103: =IFERROR(SUMIF(Table4[Item ID],'Inventory calculations'!A103,Table4[Quantity Purchased]),0) -> 30 | K103: =H103+J103-I103 -> 790 | L103: =IF(K103<0,"STOCK ISSUE","OK") -> OK | M103: =K103*E103 -> 892834.3 | N103: =Table5[[#This Row],[Total Qty Sold]]*Table5[[#This Row],[Unit Price]] -> 8536.75 | O103: =IFERROR(_xlfn.MAXIFS(Table3[Date],Table3[Item ID],Table5[[#This Row],[Item ID]]),"") -> 45302 | P103: =IF(Table5[[#This Row],[Last sale Date]]="","Never Sold",TODAY()-Table5[[#This Row],[Last sale Date]]) -> 750 | Q103: =IF(Table5[[#This Row],[Re order Level]]<=Table5[[#This Row],[Current stock]],"ORDERASAP","OK BUT BE CHECKING") -> OK BUT BE CHECKING | R103: =IF(AND(ISNUMBER(B103), B103 > 60), "DEAD", "ACTIVE") -> ACTIVE | S103: =IF(Table5[[#This Row],[DEADSTOCK FLAG]]="DEAD",Table5[[#This Row],[Inventory Value]],0) -> 0
A104: ='Inventory master'!A104 -> ITEM103-A | B104: ='Inventory master'!B104 -> CFP Transceiver | C104: ='Inventory master'!C104 -> Transceivers | D104: ='Inventory master'!D104 -> HellermannTyton | E104: ='Inventory master'!E104 -> 1679.29 | F104: ='Inventory master'!F104 -> 2166.75 | G104: ='Inventory master'!G104 -> 28 | H104: =IFERROR(_xlfn.XLOOKUP(A104, 'Opening stock'!A104:A703, 'Opening stock'!E104:E703), "") -> 420 | I104: =IFERROR(SUMIF(Table3[Item ID],'Inventory calculations'!A104,Table3[Quantity]),0) -> 0 | J104: =IFERROR(SUMIF(Table4[Item ID],'Inventory calculations'!A104,Table4[Quantity Purchased]),0) -> 11 | K104: =H104+J104-I104 -> 431 | L104: =IF(K104<0,"STOCK ISSUE","OK") -> OK | M104: =K104*E104 -> 723773.99 | N104: =Table5[[#This Row],[Total Qty Sold]]*Table5[[#This Row],[Unit Price]] -> 0 | O104: =IFERROR(_xlfn.MAXIFS(Table3[Date],Table3[Item ID],Table5[[#This Row],[Item ID]]),"") -> 0 | P104: =IF(Table5[[#This Row],[Last sale Date]]="","Never Sold",TODAY()-Table5[[#This Row],[Last sale Date]]) -> 46052 | Q104: =IF(Table5[[#This Row],[Re order Level]]<=Table5[[#This Row],[Current stock]],"ORDERASAP","OK BUT BE CHECKING") -> OK BUT BE CHECKING | R104: =IF(AND(ISNUMBER(B104), B104 > 60), "DEAD", "ACTIVE") -> ACTIVE | S104: =IF(Table5[[#This Row],[DEADSTOCK FLAG]]="DEAD",Table5[[#This Row],[Inventory Value]],0) -> 0
A105: ='Inventory master'!A105 -> ITEM104-A | B105: ='Inventory master'!B105 -> Dome Enclosure | C105: ='Inventory master'!C105 -> Enclosures | D105: ='Inventory master'!D105 -> Corning Inc. | E105: ='Inventory master'!E105 -> 281.54 | F105: ='Inventory master'!F105 -> 400.04 | G105: ='Inventory master'!G105 -> 91 | H105: =IFERROR(_xlfn.XLOOKUP(A105, 'Opening stock'!A105:A704, 'Opening stock'!E105:E704), "") -> 1365 | I105: =IFERROR(SUMIF(Table3[Item ID],'Inventory calculations'!A105,Table3[Quantity]),0) -> 9 | J105: =IFERROR(SUMIF(Table4[Item ID],'Inventory calculations'!A105,Table4[Quantity Purchased]),0) -> 9 | K105: =H105+J105-I105 -> 1365 | L105: =IF(K105<0,"STOCK ISSUE","OK") -> OK | M105: =K105*E105 -> 384302.1 | N105: =Table5[[#This Row],[Total Qty Sold]]*Table5[[#This Row],[Unit Price]] -> 3600.36 | O105: =IFERROR(_xlfn.MAXIFS(Table3[Date],Table3[Item ID],Table5[[#This Row],[Item ID]]),"") -> 45763 | P105: =IF(Table5[[#This Row],[Last sale Date]]="","Never Sold",TODAY()-Table5[[#This Row],[Last sale Date]]) -> 289 | Q105: =IF(Table5[[#This Row],[Re order Level]]<=Table5[[#This Row],[Current stock]],"ORDERASAP","OK BUT BE CHECKING") -> OK BUT BE CHECKING | R105: =IF(AND(ISNUMBER(B105), B105 > 60), "DEAD", "ACTIVE") -> ACTIVE | S105: =IF(Table5[[#This Row],[DEADSTOCK FLAG]]="DEAD",Table5[[#This Row],[Inventory Value]],0) -> 0
A106: ='Inventory master'!A106 -> ITEM105-A | B106: ='Inventory master'!B106 -> MPO APC Connector | C106: ='Inventory master'!C106 -> Connectors | D106: ='Inventory master'!D106 -> Huber+Suhner | E106: ='Inventory master'!E106 -> 1262.28 | F106: ='Inventory master'!F106 -> 1963.72 | G106: ='Inventory master'!G106 -> 13 | H106: =IFERROR(_xlfn.XLOOKUP(A106, 'Opening stock'!A106:A705, 'Opening stock'!E106:E705), "") -> 195 | I106: =IFERROR(SUMIF(Table3[Item ID],'Inventory calculations'!A106,Table3[Quantity]),0) -> 0 | J106: =IFERROR(SUMIF(Table4[Item ID],'Inventory calculations'!A106,Table4[Quantity Purchased]),0) -> 8 | K106: =H106+J106-I106 -> 203 | L106: =IF(K106<0,"STOCK ISSUE","OK") -> OK | M106: =K106*E106 -> 256242.84 | N106: =Table5[[#This Row],[Total Qty Sold]]*Table5[[#This Row],[Unit Price]] -> 0 | P106: =IF(Table5[[#This Row],[Last sale Date]]="","Never Sold",TODAY()-Table5[[#This Row],[Last sale Date]]) -> Never Sold | Q106: =IF(Table5[[#This Row],[Re order Level]]<=Table5[[#This Row],[Current stock]],"ORDERASAP","OK BUT BE CHECKING") -> OK BUT BE CHECKING | R106: =IF(AND(ISNUMBER(B106), B106 > 60), "DEAD", "ACTIVE") -> ACTIVE | S106: =IF(Table5[[#This Row],[DEADSTOCK FLAG]]="DEAD",Table5[[#This Row],[Inventory Value]],0) -> 0
A107: ='Inventory master'!A107 -> ITEM106-A | B107: ='Inventory master'!B107 -> 1x4 PLC Splitter | C107: ='Inventory master'!C107 -> Splitters | D107: ='Inventory master'!D107 -> CommScope | E107: ='Inventory master'!E107 -> 450.83 | F107: ='Inventory master'!F107 -> 520.66 | G107: ='Inventory master'!G107 -> 67 | H107: =IFERROR(_xlfn.XLOOKUP(A107, 'Opening stock'!A107:A706, 'Opening stock'!E107:E706), "") -> 1005 | I107: =IFERROR(SUMIF(Table3[Item ID],'Inventory calculations'!A107,Table3[Quantity]),0) -> 0 | J107: =IFERROR(SUMIF(Table4[Item ID],'Inventory calculations'!A107,Table4[Quantity Purchased]),0) -> 10 | K107: =H107+J107-I107 -> 1015 | L107: =IF(K107<0,"STOCK ISSUE","OK") -> OK | M107: =K107*E107 -> 457592.45 | N107: =Table5[[#This Row],[Total Qty Sold]]*Table5[[#This Row],[Unit Price]] -> 0 | P107: =IF(Table5[[#This Row],[Last sale Date]]="","Never Sold",TODAY()-Table5[[#This Row],[Last sale Date]]) -> Never Sold | Q107: =IF(Table5[[#This Row],[Re order Level]]<=Table5[[#This Row],[Current stock]],"ORDERASAP","OK BUT BE CHECKING") -> OK BUT BE CHECKING | R107: =IF(AND(ISNUMBER(B107), B107 > 60), "DEAD", "ACTIVE") -> ACTIVE | S107: =IF(Table5[[#This Row],[DEADSTOCK FLAG]]="DEAD",Table5[[#This Row],[Inventory Value]],0) -> 0
A108: ='Inventory master'!A108 -> ITEM107-A | B108: ='Inventory master'!B108 -> Armored Fiber Cable 500m | C108: ='Inventory master'!C108 -> Fiber Optic Cables | D108: ='Inventory master'!D108 -> HellermannTyton | E108: ='Inventory master'!E108 -> 1093.91 | F108: ='Inventory master'!F108 -> 1623.2 | G108: ='Inventory master'!G108 -> 12 | H108: =IFERROR(_xlfn.XLOOKUP(A108, 'Opening stock'!A108:A707, 'Opening stock'!E108:E707), "") -> 180 | I108: =IFERROR(SUMIF(Table3[Item ID],'Inventory calculations'!A108,Table3[Quantity]),0) -> 0 | J108: =IFERROR(SUMIF(Table4[Item ID],'Inventory calculations'!A108,Table4[Quantity Purchased]),0) -> 10 | K108: =H108+J108-I108 -> 190 | L108: =IF(K108<0,"STOCK ISSUE","OK") -> OK | M108: =K108*E108 -> 207842.9 | N108: =Table5[[#This Row],[Total Qty Sold]]*Table5[[#This Row],[Unit Price]] -> 0 | P108: =IF(Table5[[#This Row],[Last sale Date]]="","Never Sold",TODAY()-Table5[[#This Row],[Last sale Date]]) -> Never Sold | Q108: =IF(Table5[[#This Row],[Re order Level]]<=Table5[[#This Row],[Current stock]],"ORDERASAP","OK BUT BE CHECKING") -> OK BUT BE CHECKING | R108: =IF(AND(ISNUMBER(B108), B108 > 60), "DEAD", "ACTIVE") -> ACTIVE | S108: =IF(Table5[[#This Row],[DEADSTOCK FLAG]]="DEAD",Table5[[#This Row],[Inventory Value]],0) -> 0
...

Sheet Dashboard tables
A1: Chart 1: Sales Trend Over Time
A2: Row Labels | B2: Sum of Quantity
A3: Jan | B3: 373
A4: Feb | B4: 389
A5: Mar | B5: 463
A6: Apr | B6: 389
A7: May | B7: 363
A8: Jun | B8: 849
A9: Jul | B9: 366
A10: Aug | B10: 499
A11: Sep | B11: 429
A12: Oct | B12: 498
A13: Nov | B13: 369
A14: Dec | B14: 362
A15: Grand Total | B15: 5349
A17: Top-Selling Products
A18: Row Labels | B18: Sum of Total Qty Sold
A19: 12-Port Fiber Patch Panel | B19: 261
A20: 1x16 PLC Splitter | B20: 443
A21: 1x2 PLC Splitter | B21: 0
A22: 1x32 PLC Splitter | B22: 55
A23: 1x4 PLC Splitter | B23: 12
A24: 1x8 PLC Splitter | B24: 132
A25: 24-Port Fiber Patch Panel | B25: 0
A26: 48-Port Fiber Patch Panel | B26: 144
A27: 72-Port Fiber Patch Panel | B27: 163
A28: 96-Port Fiber Patch Panel | B28: 25
A29: Armored Fiber Cable 100m | B29: 0
A30: Armored Fiber Cable 200m | B30: 0
... A91: Grand Total | B91: 5324
